{
  "page": "db_extradata.html",
  "js_file": "/Users/nimrod/Documents/TikTrack/TikTrackApp/trading-ui/scripts/db_extradata.js",
  "html_file": "/Users/nimrod/Documents/TikTrack/TikTrackApp/trading-ui/db_extradata.html",
  "categories": {
    "unified_init": {
      "status": "missing",
      "issues": [
        {
          "line": 456,
          "content": "<script src=\"scripts/init-system/package-manifest.js?v=1.0.0\"></script> <!-- Package manifest -->",
          "pattern": "package-manifest\\.js",
          "match": "package-manifest.js",
          "file": "html"
        },
        {
          "line": 458,
          "content": "<script src=\"scripts/page-initialization-configs.js?v=1.0.0\"></script> <!-- Page initialization conf",
          "pattern": "page-initialization-configs\\.js",
          "match": "page-initialization-configs.js",
          "file": "html"
        }
      ],
      "issue_count": 2,
      "js_result": {
        "status": "missing",
        "issues": [],
        "issue_count": 0
      },
      "html_result": {
        "status": "missing",
        "issues": [
          {
            "line": 456,
            "content": "<script src=\"scripts/init-system/package-manifest.js?v=1.0.0\"></script> <!-- Package manifest -->",
            "pattern": "package-manifest\\.js",
            "match": "package-manifest.js"
          },
          {
            "line": 458,
            "content": "<script src=\"scripts/page-initialization-configs.js?v=1.0.0\"></script> <!-- Page initialization conf",
            "pattern": "page-initialization-configs\\.js",
            "match": "page-initialization-configs.js"
          }
        ],
        "issue_count": 2
      }
    },
    "section_toggle": {
      "status": "ok",
      "issues": [
        {
          "line": 435,
          "content": "// toggleSection removed - using global version from ui-utils.js",
          "pattern": "toggleSection",
          "match": "toggleSection",
          "file": "js"
        },
        {
          "line": 53,
          "content": "<div class=\"top-section\" data-section=\"top\">",
          "pattern": "data-section",
          "match": "data-section",
          "file": "html"
        },
        {
          "line": 82,
          "content": "<div class=\"content-section db-display-table\" id=\"constraintsSection\" data-section=\"constraintsSecti",
          "pattern": "data-section",
          "match": "data-section",
          "file": "html"
        },
        {
          "line": 105,
          "content": "<div class=\"content-section db-display-table\" id=\"currenciesSection\" data-section=\"currenciesSection",
          "pattern": "data-section",
          "match": "data-section",
          "file": "html"
        },
        {
          "line": 128,
          "content": "<div class=\"content-section db-display-table\" id=\"preferenceGroupsSection\" data-section=\"preferenceG",
          "pattern": "data-section",
          "match": "data-section",
          "file": "html"
        },
        {
          "line": 151,
          "content": "<div class=\"content-section db-display-table\" id=\"systemSettingGroupsSection\" data-section=\"systemSe",
          "pattern": "data-section",
          "match": "data-section",
          "file": "html"
        },
        {
          "line": 174,
          "content": "<div class=\"content-section db-display-table\" id=\"externalDataProvidersSection\" data-section=\"extern",
          "pattern": "data-section",
          "match": "data-section",
          "file": "html"
        },
        {
          "line": 197,
          "content": "<div class=\"content-section db-display-table\" id=\"quotesLastSection\" data-section=\"quotesLastSection",
          "pattern": "data-section",
          "match": "data-section",
          "file": "html"
        },
        {
          "line": 220,
          "content": "<div class=\"content-section db-display-table\" id=\"planConditionsSection\" data-section=\"planCondition",
          "pattern": "data-section",
          "match": "data-section",
          "file": "html"
        },
        {
          "line": 243,
          "content": "<div class=\"content-section db-display-table\" id=\"userPreferencesSection\" data-section=\"userPreferen",
          "pattern": "data-section",
          "match": "data-section",
          "file": "html"
        },
        {
          "line": 61,
          "content": "<button data-button-type=\"TOGGLE\" data-variant=\"small\" data-onclick=\"toggleSection('top'))\" data-cla",
          "pattern": "toggleSection",
          "match": "toggleSection",
          "file": "html"
        },
        {
          "line": 90,
          "content": "<button data-button-type=\"TOGGLE\" data-variant=\"small\" data-onclick=\"toggleSection('constraintsSecti",
          "pattern": "toggleSection",
          "match": "toggleSection",
          "file": "html"
        },
        {
          "line": 113,
          "content": "<button data-button-type=\"TOGGLE\" data-variant=\"small\" data-onclick=\"toggleSection('currenciesSectio",
          "pattern": "toggleSection",
          "match": "toggleSection",
          "file": "html"
        },
        {
          "line": 136,
          "content": "<button data-button-type=\"TOGGLE\" data-variant=\"small\" data-onclick=\"toggleSection('preferenceGroups",
          "pattern": "toggleSection",
          "match": "toggleSection",
          "file": "html"
        },
        {
          "line": 159,
          "content": "<button data-button-type=\"TOGGLE\" data-variant=\"small\" data-onclick=\"toggleSection('systemSettingGro",
          "pattern": "toggleSection",
          "match": "toggleSection",
          "file": "html"
        },
        {
          "line": 182,
          "content": "<button data-button-type=\"TOGGLE\" data-variant=\"small\" data-onclick=\"toggleSection('externalDataProv",
          "pattern": "toggleSection",
          "match": "toggleSection",
          "file": "html"
        },
        {
          "line": 205,
          "content": "<button data-button-type=\"TOGGLE\" data-variant=\"small\" data-onclick=\"toggleSection('quotesLastSectio",
          "pattern": "toggleSection",
          "match": "toggleSection",
          "file": "html"
        },
        {
          "line": 228,
          "content": "<button data-button-type=\"TOGGLE\" data-variant=\"small\" data-onclick=\"toggleSection('planConditionsSe",
          "pattern": "toggleSection",
          "match": "toggleSection",
          "file": "html"
        },
        {
          "line": 251,
          "content": "<button data-button-type=\"TOGGLE\" data-variant=\"small\" data-onclick=\"toggleSection('userPreferencesS",
          "pattern": "toggleSection",
          "match": "toggleSection",
          "file": "html"
        }
      ],
      "issue_count": 19,
      "js_result": {
        "status": "ok",
        "issues": [
          {
            "line": 435,
            "content": "// toggleSection removed - using global version from ui-utils.js",
            "pattern": "toggleSection",
            "match": "toggleSection"
          }
        ],
        "issue_count": 1
      },
      "html_result": {
        "status": "ok",
        "issues": [
          {
            "line": 53,
            "content": "<div class=\"top-section\" data-section=\"top\">",
            "pattern": "data-section",
            "match": "data-section"
          },
          {
            "line": 82,
            "content": "<div class=\"content-section db-display-table\" id=\"constraintsSection\" data-section=\"constraintsSecti",
            "pattern": "data-section",
            "match": "data-section"
          },
          {
            "line": 105,
            "content": "<div class=\"content-section db-display-table\" id=\"currenciesSection\" data-section=\"currenciesSection",
            "pattern": "data-section",
            "match": "data-section"
          },
          {
            "line": 128,
            "content": "<div class=\"content-section db-display-table\" id=\"preferenceGroupsSection\" data-section=\"preferenceG",
            "pattern": "data-section",
            "match": "data-section"
          },
          {
            "line": 151,
            "content": "<div class=\"content-section db-display-table\" id=\"systemSettingGroupsSection\" data-section=\"systemSe",
            "pattern": "data-section",
            "match": "data-section"
          },
          {
            "line": 174,
            "content": "<div class=\"content-section db-display-table\" id=\"externalDataProvidersSection\" data-section=\"extern",
            "pattern": "data-section",
            "match": "data-section"
          },
          {
            "line": 197,
            "content": "<div class=\"content-section db-display-table\" id=\"quotesLastSection\" data-section=\"quotesLastSection",
            "pattern": "data-section",
            "match": "data-section"
          },
          {
            "line": 220,
            "content": "<div class=\"content-section db-display-table\" id=\"planConditionsSection\" data-section=\"planCondition",
            "pattern": "data-section",
            "match": "data-section"
          },
          {
            "line": 243,
            "content": "<div class=\"content-section db-display-table\" id=\"userPreferencesSection\" data-section=\"userPreferen",
            "pattern": "data-section",
            "match": "data-section"
          },
          {
            "line": 61,
            "content": "<button data-button-type=\"TOGGLE\" data-variant=\"small\" data-onclick=\"toggleSection('top'))\" data-cla",
            "pattern": "toggleSection",
            "match": "toggleSection"
          },
          {
            "line": 90,
            "content": "<button data-button-type=\"TOGGLE\" data-variant=\"small\" data-onclick=\"toggleSection('constraintsSecti",
            "pattern": "toggleSection",
            "match": "toggleSection"
          },
          {
            "line": 113,
            "content": "<button data-button-type=\"TOGGLE\" data-variant=\"small\" data-onclick=\"toggleSection('currenciesSectio",
            "pattern": "toggleSection",
            "match": "toggleSection"
          },
          {
            "line": 136,
            "content": "<button data-button-type=\"TOGGLE\" data-variant=\"small\" data-onclick=\"toggleSection('preferenceGroups",
            "pattern": "toggleSection",
            "match": "toggleSection"
          },
          {
            "line": 159,
            "content": "<button data-button-type=\"TOGGLE\" data-variant=\"small\" data-onclick=\"toggleSection('systemSettingGro",
            "pattern": "toggleSection",
            "match": "toggleSection"
          },
          {
            "line": 182,
            "content": "<button data-button-type=\"TOGGLE\" data-variant=\"small\" data-onclick=\"toggleSection('externalDataProv",
            "pattern": "toggleSection",
            "match": "toggleSection"
          },
          {
            "line": 205,
            "content": "<button data-button-type=\"TOGGLE\" data-variant=\"small\" data-onclick=\"toggleSection('quotesLastSectio",
            "pattern": "toggleSection",
            "match": "toggleSection"
          },
          {
            "line": 228,
            "content": "<button data-button-type=\"TOGGLE\" data-variant=\"small\" data-onclick=\"toggleSection('planConditionsSe",
            "pattern": "toggleSection",
            "match": "toggleSection"
          },
          {
            "line": 251,
            "content": "<button data-button-type=\"TOGGLE\" data-variant=\"small\" data-onclick=\"toggleSection('userPreferencesS",
            "pattern": "toggleSection",
            "match": "toggleSection"
          }
        ],
        "issue_count": 18
      }
    },
    "notifications": {
      "status": "ok",
      "issues": [],
      "issue_count": 0,
      "js_result": {
        "status": "ok",
        "issues": [],
        "issue_count": 0
      },
      "html_result": {
        "status": "ok",
        "issues": [],
        "issue_count": 0
      }
    },
    "modals": {
      "status": "ok",
      "issues": [],
      "issue_count": 0,
      "js_result": {
        "status": "ok",
        "issues": [],
        "issue_count": 0
      },
      "html_result": {
        "status": "ok",
        "issues": [],
        "issue_count": 0
      }
    },
    "tables": {
      "status": "missing",
      "issues": [
        {
          "line": 238,
          "content": "* Create table headers from data (FALLBACK - Use UnifiedTableSystem instead)",
          "pattern": "UnifiedTableSystem",
          "match": "UnifiedTableSystem",
          "file": "js"
        },
        {
          "line": 239,
          "content": "* @deprecated Use window.UnifiedTableSystem.renderer.render() instead",
          "pattern": "UnifiedTableSystem",
          "match": "UnifiedTableSystem",
          "file": "js"
        },
        {
          "line": 257,
          "content": "* Create table rows from data (FALLBACK - Use UnifiedTableSystem instead)",
          "pattern": "UnifiedTableSystem",
          "match": "UnifiedTableSystem",
          "file": "js"
        },
        {
          "line": 258,
          "content": "* @deprecated Use window.UnifiedTableSystem.renderer.render() instead",
          "pattern": "UnifiedTableSystem",
          "match": "UnifiedTableSystem",
          "file": "js"
        },
        {
          "line": 95,
          "content": "<table class=\"table\" id=\"constraintsTable\" data-table-type=\"constraints\">",
          "pattern": "data-table-type",
          "match": "data-table-type",
          "file": "html"
        },
        {
          "line": 118,
          "content": "<table class=\"table\" id=\"currenciesTable\" data-table-type=\"currencies\">",
          "pattern": "data-table-type",
          "match": "data-table-type",
          "file": "html"
        },
        {
          "line": 141,
          "content": "<table class=\"table\" id=\"preferenceGroupsTable\" data-table-type=\"preference_groups\">",
          "pattern": "data-table-type",
          "match": "data-table-type",
          "file": "html"
        },
        {
          "line": 164,
          "content": "<table class=\"table\" id=\"systemSettingGroupsTable\" data-table-type=\"system_setting_groups\">",
          "pattern": "data-table-type",
          "match": "data-table-type",
          "file": "html"
        },
        {
          "line": 187,
          "content": "<table class=\"table\" id=\"externalDataProvidersTable\" data-table-type=\"external_data_providers\">",
          "pattern": "data-table-type",
          "match": "data-table-type",
          "file": "html"
        },
        {
          "line": 210,
          "content": "<table class=\"table\" id=\"quotesLastTable\" data-table-type=\"quotes_last\">",
          "pattern": "data-table-type",
          "match": "data-table-type",
          "file": "html"
        },
        {
          "line": 233,
          "content": "<table class=\"table\" id=\"planConditionsTable\" data-table-type=\"plan_conditions\">",
          "pattern": "data-table-type",
          "match": "data-table-type",
          "file": "html"
        },
        {
          "line": 256,
          "content": "<table class=\"table\" id=\"userPreferencesTable\" data-table-type=\"user_preferences\">",
          "pattern": "data-table-type",
          "match": "data-table-type",
          "file": "html"
        }
      ],
      "issue_count": 12,
      "js_result": {
        "status": "missing",
        "issues": [
          {
            "line": 238,
            "content": "* Create table headers from data (FALLBACK - Use UnifiedTableSystem instead)",
            "pattern": "UnifiedTableSystem",
            "match": "UnifiedTableSystem"
          },
          {
            "line": 239,
            "content": "* @deprecated Use window.UnifiedTableSystem.renderer.render() instead",
            "pattern": "UnifiedTableSystem",
            "match": "UnifiedTableSystem"
          },
          {
            "line": 257,
            "content": "* Create table rows from data (FALLBACK - Use UnifiedTableSystem instead)",
            "pattern": "UnifiedTableSystem",
            "match": "UnifiedTableSystem"
          },
          {
            "line": 258,
            "content": "* @deprecated Use window.UnifiedTableSystem.renderer.render() instead",
            "pattern": "UnifiedTableSystem",
            "match": "UnifiedTableSystem"
          }
        ],
        "issue_count": 4
      },
      "html_result": {
        "status": "ok",
        "issues": [
          {
            "line": 95,
            "content": "<table class=\"table\" id=\"constraintsTable\" data-table-type=\"constraints\">",
            "pattern": "data-table-type",
            "match": "data-table-type"
          },
          {
            "line": 118,
            "content": "<table class=\"table\" id=\"currenciesTable\" data-table-type=\"currencies\">",
            "pattern": "data-table-type",
            "match": "data-table-type"
          },
          {
            "line": 141,
            "content": "<table class=\"table\" id=\"preferenceGroupsTable\" data-table-type=\"preference_groups\">",
            "pattern": "data-table-type",
            "match": "data-table-type"
          },
          {
            "line": 164,
            "content": "<table class=\"table\" id=\"systemSettingGroupsTable\" data-table-type=\"system_setting_groups\">",
            "pattern": "data-table-type",
            "match": "data-table-type"
          },
          {
            "line": 187,
            "content": "<table class=\"table\" id=\"externalDataProvidersTable\" data-table-type=\"external_data_providers\">",
            "pattern": "data-table-type",
            "match": "data-table-type"
          },
          {
            "line": 210,
            "content": "<table class=\"table\" id=\"quotesLastTable\" data-table-type=\"quotes_last\">",
            "pattern": "data-table-type",
            "match": "data-table-type"
          },
          {
            "line": 233,
            "content": "<table class=\"table\" id=\"planConditionsTable\" data-table-type=\"plan_conditions\">",
            "pattern": "data-table-type",
            "match": "data-table-type"
          },
          {
            "line": 256,
            "content": "<table class=\"table\" id=\"userPreferencesTable\" data-table-type=\"user_preferences\">",
            "pattern": "data-table-type",
            "match": "data-table-type"
          }
        ],
        "issue_count": 8
      }
    },
    "field_renderer": {
      "status": "missing",
      "issues": [],
      "issue_count": 0,
      "js_result": {
        "status": "missing",
        "issues": [],
        "issue_count": 0
      },
      "html_result": {
        "status": "missing",
        "issues": [],
        "issue_count": 0
      }
    },
    "crud_handler": {
      "status": "missing",
      "issues": [],
      "issue_count": 0,
      "js_result": {
        "status": "missing",
        "issues": [],
        "issue_count": 0
      },
      "html_result": {
        "status": "missing",
        "issues": [],
        "issue_count": 0
      }
    },
    "select_populator": {
      "status": "missing",
      "issues": [],
      "issue_count": 0,
      "js_result": {
        "status": "missing",
        "issues": [],
        "issue_count": 0
      },
      "html_result": {
        "status": "missing",
        "issues": [],
        "issue_count": 0
      }
    },
    "data_collection": {
      "status": "missing",
      "issues": [],
      "issue_count": 0,
      "js_result": {
        "status": "missing",
        "issues": [],
        "issue_count": 0
      },
      "html_result": {
        "status": "missing",
        "issues": [],
        "issue_count": 0
      }
    },
    "icons": {
      "status": "missing",
      "issues": [
        {
          "line": 37,
          "content": "<!-- Bootstrap Icons and FontAwesome removed - using Tabler Icons via IconSystem -->",
          "pattern": "IconSystem",
          "match": "IconSystem",
          "file": "html"
        },
        {
          "line": 57,
          "content": "<img src=\"images/icons/entities/development.svg\" alt=\"טבלאות עזר\" class=\"section-icon\">",
          "pattern": "<img.*icon",
          "match": "<img src=\"images/icons/entities/development.svg\" a",
          "file": "html"
        },
        {
          "line": 85,
          "content": "<img src=\"images/icons/entities/development.svg\" alt=\"constraints\" class=\"section-icon\">",
          "pattern": "<img.*icon",
          "match": "<img src=\"images/icons/entities/development.svg\" a",
          "file": "html"
        },
        {
          "line": 108,
          "content": "<img src=\"images/icons/entities/development.svg\" alt=\"currencies\" class=\"section-icon\">",
          "pattern": "<img.*icon",
          "match": "<img src=\"images/icons/entities/development.svg\" a",
          "file": "html"
        },
        {
          "line": 131,
          "content": "<img src=\"images/icons/entities/development.svg\" alt=\"preference_groups\" class=\"section-icon\">",
          "pattern": "<img.*icon",
          "match": "<img src=\"images/icons/entities/development.svg\" a",
          "file": "html"
        },
        {
          "line": 154,
          "content": "<img src=\"images/icons/entities/development.svg\" alt=\"system_setting_groups\" class=\"section-icon\">",
          "pattern": "<img.*icon",
          "match": "<img src=\"images/icons/entities/development.svg\" a",
          "file": "html"
        },
        {
          "line": 177,
          "content": "<img src=\"images/icons/entities/development.svg\" alt=\"external_data_providers\" class=\"section-icon\">",
          "pattern": "<img.*icon",
          "match": "<img src=\"images/icons/entities/development.svg\" a",
          "file": "html"
        },
        {
          "line": 200,
          "content": "<img src=\"images/icons/entities/development.svg\" alt=\"quotes_last\" class=\"section-icon\">",
          "pattern": "<img.*icon",
          "match": "<img src=\"images/icons/entities/development.svg\" a",
          "file": "html"
        },
        {
          "line": 223,
          "content": "<img src=\"images/icons/entities/development.svg\" alt=\"plan_conditions\" class=\"section-icon\">",
          "pattern": "<img.*icon",
          "match": "<img src=\"images/icons/entities/development.svg\" a",
          "file": "html"
        },
        {
          "line": 246,
          "content": "<img src=\"images/icons/entities/development.svg\" alt=\"user_preferences\" class=\"section-icon\">",
          "pattern": "<img.*icon",
          "match": "<img src=\"images/icons/entities/development.svg\" a",
          "file": "html"
        }
      ],
      "issue_count": 10,
      "js_result": {
        "status": "missing",
        "issues": [],
        "issue_count": 0
      },
      "html_result": {
        "status": "ok",
        "issues": [
          {
            "line": 37,
            "content": "<!-- Bootstrap Icons and FontAwesome removed - using Tabler Icons via IconSystem -->",
            "pattern": "IconSystem",
            "match": "IconSystem"
          },
          {
            "line": 57,
            "content": "<img src=\"images/icons/entities/development.svg\" alt=\"טבלאות עזר\" class=\"section-icon\">",
            "pattern": "<img.*icon",
            "match": "<img src=\"images/icons/entities/development.svg\" a"
          },
          {
            "line": 85,
            "content": "<img src=\"images/icons/entities/development.svg\" alt=\"constraints\" class=\"section-icon\">",
            "pattern": "<img.*icon",
            "match": "<img src=\"images/icons/entities/development.svg\" a"
          },
          {
            "line": 108,
            "content": "<img src=\"images/icons/entities/development.svg\" alt=\"currencies\" class=\"section-icon\">",
            "pattern": "<img.*icon",
            "match": "<img src=\"images/icons/entities/development.svg\" a"
          },
          {
            "line": 131,
            "content": "<img src=\"images/icons/entities/development.svg\" alt=\"preference_groups\" class=\"section-icon\">",
            "pattern": "<img.*icon",
            "match": "<img src=\"images/icons/entities/development.svg\" a"
          },
          {
            "line": 154,
            "content": "<img src=\"images/icons/entities/development.svg\" alt=\"system_setting_groups\" class=\"section-icon\">",
            "pattern": "<img.*icon",
            "match": "<img src=\"images/icons/entities/development.svg\" a"
          },
          {
            "line": 177,
            "content": "<img src=\"images/icons/entities/development.svg\" alt=\"external_data_providers\" class=\"section-icon\">",
            "pattern": "<img.*icon",
            "match": "<img src=\"images/icons/entities/development.svg\" a"
          },
          {
            "line": 200,
            "content": "<img src=\"images/icons/entities/development.svg\" alt=\"quotes_last\" class=\"section-icon\">",
            "pattern": "<img.*icon",
            "match": "<img src=\"images/icons/entities/development.svg\" a"
          },
          {
            "line": 223,
            "content": "<img src=\"images/icons/entities/development.svg\" alt=\"plan_conditions\" class=\"section-icon\">",
            "pattern": "<img.*icon",
            "match": "<img src=\"images/icons/entities/development.svg\" a"
          },
          {
            "line": 246,
            "content": "<img src=\"images/icons/entities/development.svg\" alt=\"user_preferences\" class=\"section-icon\">",
            "pattern": "<img.*icon",
            "match": "<img src=\"images/icons/entities/development.svg\" a"
          }
        ],
        "issue_count": 10
      }
    },
    "colors": {
      "status": "missing",
      "issues": [],
      "issue_count": 0,
      "js_result": {
        "status": "missing",
        "issues": [],
        "issue_count": 0
      },
      "html_result": {
        "status": "missing",
        "issues": [],
        "issue_count": 0
      }
    },
    "info_summary": {
      "status": "missing",
      "issues": [],
      "issue_count": 0,
      "js_result": {
        "status": "missing",
        "issues": [],
        "issue_count": 0
      },
      "html_result": {
        "status": "missing",
        "issues": [],
        "issue_count": 0
      }
    },
    "pagination": {
      "status": "missing",
      "issues": [],
      "issue_count": 0,
      "js_result": {
        "status": "missing",
        "issues": [],
        "issue_count": 0
      },
      "html_result": {
        "status": "missing",
        "issues": [],
        "issue_count": 0
      }
    },
    "entity_details": {
      "status": "missing",
      "issues": [],
      "issue_count": 0,
      "js_result": {
        "status": "missing",
        "issues": [],
        "issue_count": 0
      },
      "html_result": {
        "status": "missing",
        "issues": [],
        "issue_count": 0
      }
    },
    "conditions": {
      "status": "missing",
      "issues": [],
      "issue_count": 0,
      "js_result": {
        "status": "missing",
        "issues": [],
        "issue_count": 0
      },
      "html_result": {
        "status": "missing",
        "issues": [],
        "issue_count": 0
      }
    },
    "page_state": {
      "status": "ok",
      "issues": [],
      "issue_count": 0,
      "js_result": {
        "status": "ok",
        "issues": [],
        "issue_count": 0
      },
      "html_result": {
        "status": "ok",
        "issues": [],
        "issue_count": 0
      }
    },
    "logger": {
      "status": "ok",
      "issues": [
        {
          "line": 24,
          "content": "window.Logger?.info('Initializing database extra data page', { page: 'db_extradata' });",
          "pattern": "window\\.Logger",
          "match": "window.Logger",
          "file": "js"
        },
        {
          "line": 29,
          "content": "window.Logger?.info('Database extra data page initialized successfully', { page: 'db_extradata' });",
          "pattern": "window\\.Logger",
          "match": "window.Logger",
          "file": "js"
        },
        {
          "line": 36,
          "content": "window.Logger?.debug('Loading all extra data tables', { page: 'db_extradata' });",
          "pattern": "window\\.Logger",
          "match": "window.Logger",
          "file": "js"
        },
        {
          "line": 54,
          "content": "window.Logger?.debug('Loading table', { page: 'db_extradata', type: table.type, apiSlug: table.apiSl",
          "pattern": "window\\.Logger",
          "match": "window.Logger",
          "file": "js"
        },
        {
          "line": 58,
          "content": "window.Logger?.error('Error loading table', { page: 'db_extradata', identifier, error: error?.messag",
          "pattern": "window\\.Logger",
          "match": "window.Logger",
          "file": "js"
        },
        {
          "line": 64,
          "content": "window.Logger?.info('All extra data tables loaded', { page: 'db_extradata' });",
          "pattern": "window\\.Logger",
          "match": "window.Logger",
          "file": "js"
        },
        {
          "line": 81,
          "content": "window.Logger?.debug('Loading data for table type', { page: 'db_extradata', tableType });",
          "pattern": "window\\.Logger",
          "match": "window.Logger",
          "file": "js"
        },
        {
          "line": 100,
          "content": "window.Logger?.debug('Centralized loadTableData not available for this table type, fetching directly",
          "pattern": "window\\.Logger",
          "match": "window.Logger",
          "file": "js"
        },
        {
          "line": 139,
          "content": "window.Logger?.debug('Data loaded for table type', { page: 'db_extradata', tableType, recordCount: t",
          "pattern": "window\\.Logger",
          "match": "window.Logger",
          "file": "js"
        },
        {
          "line": 143,
          "content": "window.Logger?.error('Error loading table data', { page: 'db_extradata', identifier, error: error?.m",
          "pattern": "window\\.Logger",
          "match": "window.Logger",
          "file": "js"
        },
        {
          "line": 204,
          "content": "window.Logger?.error('Table container not found', { page: 'db_extradata', tableType, containerId });",
          "pattern": "window\\.Logger",
          "match": "window.Logger",
          "file": "js"
        },
        {
          "line": 210,
          "content": "window.Logger?.error('Table not found', { page: 'db_extradata', tableId });",
          "pattern": "window\\.Logger",
          "match": "window.Logger",
          "file": "js"
        },
        {
          "line": 216,
          "content": "window.Logger?.error('Table body not found', { page: 'db_extradata', tableId });",
          "pattern": "window\\.Logger",
          "match": "window.Logger",
          "file": "js"
        },
        {
          "line": 220,
          "content": "window.Logger?.debug('Updating table display', { page: 'db_extradata', tableType, recordCount: data.",
          "pattern": "window\\.Logger",
          "match": "window.Logger",
          "file": "js"
        },
        {
          "line": 313,
          "content": "window.Logger?.debug('No count element found', { page: 'db_extradata', countElementId });",
          "pattern": "window\\.Logger",
          "match": "window.Logger",
          "file": "js"
        },
        {
          "line": 427,
          "content": "window.Logger?.info('Database extra data page DOM loaded', { page: 'db_extradata' });",
          "pattern": "window\\.Logger",
          "match": "window.Logger",
          "file": "js"
        },
        {
          "line": 449,
          "content": "window.Logger?.info('DB Extra Data script loaded successfully', { page: 'db_extradata' });",
          "pattern": "window\\.Logger",
          "match": "window.Logger",
          "file": "js"
        },
        {
          "line": 322,
          "content": "<script src=\"scripts/logger-service.js?v=1.0.0\"></script> <!-- Advanced logging service -->",
          "pattern": "logger-service\\.js",
          "match": "logger-service.js",
          "file": "html"
        }
      ],
      "issue_count": 18,
      "js_result": {
        "status": "ok",
        "issues": [
          {
            "line": 24,
            "content": "window.Logger?.info('Initializing database extra data page', { page: 'db_extradata' });",
            "pattern": "window\\.Logger",
            "match": "window.Logger"
          },
          {
            "line": 29,
            "content": "window.Logger?.info('Database extra data page initialized successfully', { page: 'db_extradata' });",
            "pattern": "window\\.Logger",
            "match": "window.Logger"
          },
          {
            "line": 36,
            "content": "window.Logger?.debug('Loading all extra data tables', { page: 'db_extradata' });",
            "pattern": "window\\.Logger",
            "match": "window.Logger"
          },
          {
            "line": 54,
            "content": "window.Logger?.debug('Loading table', { page: 'db_extradata', type: table.type, apiSlug: table.apiSl",
            "pattern": "window\\.Logger",
            "match": "window.Logger"
          },
          {
            "line": 58,
            "content": "window.Logger?.error('Error loading table', { page: 'db_extradata', identifier, error: error?.messag",
            "pattern": "window\\.Logger",
            "match": "window.Logger"
          },
          {
            "line": 64,
            "content": "window.Logger?.info('All extra data tables loaded', { page: 'db_extradata' });",
            "pattern": "window\\.Logger",
            "match": "window.Logger"
          },
          {
            "line": 81,
            "content": "window.Logger?.debug('Loading data for table type', { page: 'db_extradata', tableType });",
            "pattern": "window\\.Logger",
            "match": "window.Logger"
          },
          {
            "line": 100,
            "content": "window.Logger?.debug('Centralized loadTableData not available for this table type, fetching directly",
            "pattern": "window\\.Logger",
            "match": "window.Logger"
          },
          {
            "line": 139,
            "content": "window.Logger?.debug('Data loaded for table type', { page: 'db_extradata', tableType, recordCount: t",
            "pattern": "window\\.Logger",
            "match": "window.Logger"
          },
          {
            "line": 143,
            "content": "window.Logger?.error('Error loading table data', { page: 'db_extradata', identifier, error: error?.m",
            "pattern": "window\\.Logger",
            "match": "window.Logger"
          },
          {
            "line": 204,
            "content": "window.Logger?.error('Table container not found', { page: 'db_extradata', tableType, containerId });",
            "pattern": "window\\.Logger",
            "match": "window.Logger"
          },
          {
            "line": 210,
            "content": "window.Logger?.error('Table not found', { page: 'db_extradata', tableId });",
            "pattern": "window\\.Logger",
            "match": "window.Logger"
          },
          {
            "line": 216,
            "content": "window.Logger?.error('Table body not found', { page: 'db_extradata', tableId });",
            "pattern": "window\\.Logger",
            "match": "window.Logger"
          },
          {
            "line": 220,
            "content": "window.Logger?.debug('Updating table display', { page: 'db_extradata', tableType, recordCount: data.",
            "pattern": "window\\.Logger",
            "match": "window.Logger"
          },
          {
            "line": 313,
            "content": "window.Logger?.debug('No count element found', { page: 'db_extradata', countElementId });",
            "pattern": "window\\.Logger",
            "match": "window.Logger"
          },
          {
            "line": 427,
            "content": "window.Logger?.info('Database extra data page DOM loaded', { page: 'db_extradata' });",
            "pattern": "window\\.Logger",
            "match": "window.Logger"
          },
          {
            "line": 449,
            "content": "window.Logger?.info('DB Extra Data script loaded successfully', { page: 'db_extradata' });",
            "pattern": "window\\.Logger",
            "match": "window.Logger"
          }
        ],
        "issue_count": 17
      },
      "html_result": {
        "status": "ok",
        "issues": [
          {
            "line": 322,
            "content": "<script src=\"scripts/logger-service.js?v=1.0.0\"></script> <!-- Advanced logging service -->",
            "pattern": "logger-service\\.js",
            "match": "logger-service.js"
          }
        ],
        "issue_count": 1
      }
    },
    "cache": {
      "status": "missing",
      "issues": [],
      "issue_count": 0,
      "js_result": {
        "status": "missing",
        "issues": [],
        "issue_count": 0
      },
      "html_result": {
        "status": "missing",
        "issues": [],
        "issue_count": 0
      }
    },
    "dom_manipulation": {
      "status": "issues_found",
      "issues": [
        {
          "line": 167,
          "content": "tbody.innerHTML = '<tr><td colspan=\"100\" class=\"text-center text-muted\">Loading data...</td></tr>';",
          "pattern": "\\.innerHTML\\s*=",
          "match": ".innerHTML =",
          "file": "js"
        },
        {
          "line": 183,
          "content": "tbody.innerHTML = `<tr><td colspan=\"100\" class=\"text-center text-danger\">Error: ${errorMessage}</td>",
          "pattern": "\\.innerHTML\\s*=",
          "match": ".innerHTML =",
          "file": "js"
        },
        {
          "line": 226,
          "content": "thead.innerHTML = headers;",
          "pattern": "\\.innerHTML\\s*=",
          "match": ".innerHTML =",
          "file": "js"
        },
        {
          "line": 231,
          "content": "tbody.innerHTML = rows;",
          "pattern": "\\.innerHTML\\s*=",
          "match": ".innerHTML =",
          "file": "js"
        }
      ],
      "issue_count": 4,
      "js_result": {
        "status": "issues_found",
        "issues": [
          {
            "line": 167,
            "content": "tbody.innerHTML = '<tr><td colspan=\"100\" class=\"text-center text-muted\">Loading data...</td></tr>';",
            "pattern": "\\.innerHTML\\s*=",
            "match": ".innerHTML ="
          },
          {
            "line": 183,
            "content": "tbody.innerHTML = `<tr><td colspan=\"100\" class=\"text-center text-danger\">Error: ${errorMessage}</td>",
            "pattern": "\\.innerHTML\\s*=",
            "match": ".innerHTML ="
          },
          {
            "line": 226,
            "content": "thead.innerHTML = headers;",
            "pattern": "\\.innerHTML\\s*=",
            "match": ".innerHTML ="
          },
          {
            "line": 231,
            "content": "tbody.innerHTML = rows;",
            "pattern": "\\.innerHTML\\s*=",
            "match": ".innerHTML ="
          }
        ],
        "issue_count": 4
      },
      "html_result": {
        "status": "ok",
        "issues": [],
        "issue_count": 0
      }
    },
    "html_structure": {
      "status": "issues_found",
      "issues": [
        {
          "line": 61,
          "content": "<button data-button-type=\"TOGGLE\" data-variant=\"small\" data-onclick=\"toggleSection('top'))\" data-cla",
          "pattern": "data-onclick",
          "match": "data-onclick",
          "file": "html"
        },
        {
          "line": 90,
          "content": "<button data-button-type=\"TOGGLE\" data-variant=\"small\" data-onclick=\"toggleSection('constraintsSecti",
          "pattern": "data-onclick",
          "match": "data-onclick",
          "file": "html"
        },
        {
          "line": 113,
          "content": "<button data-button-type=\"TOGGLE\" data-variant=\"small\" data-onclick=\"toggleSection('currenciesSectio",
          "pattern": "data-onclick",
          "match": "data-onclick",
          "file": "html"
        },
        {
          "line": 136,
          "content": "<button data-button-type=\"TOGGLE\" data-variant=\"small\" data-onclick=\"toggleSection('preferenceGroups",
          "pattern": "data-onclick",
          "match": "data-onclick",
          "file": "html"
        },
        {
          "line": 159,
          "content": "<button data-button-type=\"TOGGLE\" data-variant=\"small\" data-onclick=\"toggleSection('systemSettingGro",
          "pattern": "data-onclick",
          "match": "data-onclick",
          "file": "html"
        },
        {
          "line": 182,
          "content": "<button data-button-type=\"TOGGLE\" data-variant=\"small\" data-onclick=\"toggleSection('externalDataProv",
          "pattern": "data-onclick",
          "match": "data-onclick",
          "file": "html"
        },
        {
          "line": 205,
          "content": "<button data-button-type=\"TOGGLE\" data-variant=\"small\" data-onclick=\"toggleSection('quotesLastSectio",
          "pattern": "data-onclick",
          "match": "data-onclick",
          "file": "html"
        },
        {
          "line": 228,
          "content": "<button data-button-type=\"TOGGLE\" data-variant=\"small\" data-onclick=\"toggleSection('planConditionsSe",
          "pattern": "data-onclick",
          "match": "data-onclick",
          "file": "html"
        },
        {
          "line": 251,
          "content": "<button data-button-type=\"TOGGLE\" data-variant=\"small\" data-onclick=\"toggleSection('userPreferencesS",
          "pattern": "data-onclick",
          "match": "data-onclick",
          "file": "html"
        },
        {
          "line": 61,
          "content": "<button data-button-type=\"TOGGLE\" data-variant=\"small\" data-onclick=\"toggleSection('top'))\" data-cla",
          "pattern": "data-button-type",
          "match": "data-button-type",
          "file": "html"
        },
        {
          "line": 90,
          "content": "<button data-button-type=\"TOGGLE\" data-variant=\"small\" data-onclick=\"toggleSection('constraintsSecti",
          "pattern": "data-button-type",
          "match": "data-button-type",
          "file": "html"
        },
        {
          "line": 113,
          "content": "<button data-button-type=\"TOGGLE\" data-variant=\"small\" data-onclick=\"toggleSection('currenciesSectio",
          "pattern": "data-button-type",
          "match": "data-button-type",
          "file": "html"
        },
        {
          "line": 136,
          "content": "<button data-button-type=\"TOGGLE\" data-variant=\"small\" data-onclick=\"toggleSection('preferenceGroups",
          "pattern": "data-button-type",
          "match": "data-button-type",
          "file": "html"
        },
        {
          "line": 159,
          "content": "<button data-button-type=\"TOGGLE\" data-variant=\"small\" data-onclick=\"toggleSection('systemSettingGro",
          "pattern": "data-button-type",
          "match": "data-button-type",
          "file": "html"
        },
        {
          "line": 182,
          "content": "<button data-button-type=\"TOGGLE\" data-variant=\"small\" data-onclick=\"toggleSection('externalDataProv",
          "pattern": "data-button-type",
          "match": "data-button-type",
          "file": "html"
        },
        {
          "line": 205,
          "content": "<button data-button-type=\"TOGGLE\" data-variant=\"small\" data-onclick=\"toggleSection('quotesLastSectio",
          "pattern": "data-button-type",
          "match": "data-button-type",
          "file": "html"
        },
        {
          "line": 228,
          "content": "<button data-button-type=\"TOGGLE\" data-variant=\"small\" data-onclick=\"toggleSection('planConditionsSe",
          "pattern": "data-button-type",
          "match": "data-button-type",
          "file": "html"
        },
        {
          "line": 251,
          "content": "<button data-button-type=\"TOGGLE\" data-variant=\"small\" data-onclick=\"toggleSection('userPreferencesS",
          "pattern": "data-button-type",
          "match": "data-button-type",
          "file": "html"
        },
        {
          "line": 47,
          "content": "<div id=\"unified-header\"></div>",
          "pattern": "unified-header",
          "match": "unified-header",
          "file": "html"
        }
      ],
      "issue_count": 19,
      "js_result": {
        "status": "ok",
        "issues": [],
        "issue_count": 0
      },
      "html_result": {
        "status": "issues_found",
        "issues": [
          {
            "line": 61,
            "content": "<button data-button-type=\"TOGGLE\" data-variant=\"small\" data-onclick=\"toggleSection('top'))\" data-cla",
            "pattern": "data-onclick",
            "match": "data-onclick"
          },
          {
            "line": 90,
            "content": "<button data-button-type=\"TOGGLE\" data-variant=\"small\" data-onclick=\"toggleSection('constraintsSecti",
            "pattern": "data-onclick",
            "match": "data-onclick"
          },
          {
            "line": 113,
            "content": "<button data-button-type=\"TOGGLE\" data-variant=\"small\" data-onclick=\"toggleSection('currenciesSectio",
            "pattern": "data-onclick",
            "match": "data-onclick"
          },
          {
            "line": 136,
            "content": "<button data-button-type=\"TOGGLE\" data-variant=\"small\" data-onclick=\"toggleSection('preferenceGroups",
            "pattern": "data-onclick",
            "match": "data-onclick"
          },
          {
            "line": 159,
            "content": "<button data-button-type=\"TOGGLE\" data-variant=\"small\" data-onclick=\"toggleSection('systemSettingGro",
            "pattern": "data-onclick",
            "match": "data-onclick"
          },
          {
            "line": 182,
            "content": "<button data-button-type=\"TOGGLE\" data-variant=\"small\" data-onclick=\"toggleSection('externalDataProv",
            "pattern": "data-onclick",
            "match": "data-onclick"
          },
          {
            "line": 205,
            "content": "<button data-button-type=\"TOGGLE\" data-variant=\"small\" data-onclick=\"toggleSection('quotesLastSectio",
            "pattern": "data-onclick",
            "match": "data-onclick"
          },
          {
            "line": 228,
            "content": "<button data-button-type=\"TOGGLE\" data-variant=\"small\" data-onclick=\"toggleSection('planConditionsSe",
            "pattern": "data-onclick",
            "match": "data-onclick"
          },
          {
            "line": 251,
            "content": "<button data-button-type=\"TOGGLE\" data-variant=\"small\" data-onclick=\"toggleSection('userPreferencesS",
            "pattern": "data-onclick",
            "match": "data-onclick"
          },
          {
            "line": 61,
            "content": "<button data-button-type=\"TOGGLE\" data-variant=\"small\" data-onclick=\"toggleSection('top'))\" data-cla",
            "pattern": "data-button-type",
            "match": "data-button-type"
          },
          {
            "line": 90,
            "content": "<button data-button-type=\"TOGGLE\" data-variant=\"small\" data-onclick=\"toggleSection('constraintsSecti",
            "pattern": "data-button-type",
            "match": "data-button-type"
          },
          {
            "line": 113,
            "content": "<button data-button-type=\"TOGGLE\" data-variant=\"small\" data-onclick=\"toggleSection('currenciesSectio",
            "pattern": "data-button-type",
            "match": "data-button-type"
          },
          {
            "line": 136,
            "content": "<button data-button-type=\"TOGGLE\" data-variant=\"small\" data-onclick=\"toggleSection('preferenceGroups",
            "pattern": "data-button-type",
            "match": "data-button-type"
          },
          {
            "line": 159,
            "content": "<button data-button-type=\"TOGGLE\" data-variant=\"small\" data-onclick=\"toggleSection('systemSettingGro",
            "pattern": "data-button-type",
            "match": "data-button-type"
          },
          {
            "line": 182,
            "content": "<button data-button-type=\"TOGGLE\" data-variant=\"small\" data-onclick=\"toggleSection('externalDataProv",
            "pattern": "data-button-type",
            "match": "data-button-type"
          },
          {
            "line": 205,
            "content": "<button data-button-type=\"TOGGLE\" data-variant=\"small\" data-onclick=\"toggleSection('quotesLastSectio",
            "pattern": "data-button-type",
            "match": "data-button-type"
          },
          {
            "line": 228,
            "content": "<button data-button-type=\"TOGGLE\" data-variant=\"small\" data-onclick=\"toggleSection('planConditionsSe",
            "pattern": "data-button-type",
            "match": "data-button-type"
          },
          {
            "line": 251,
            "content": "<button data-button-type=\"TOGGLE\" data-variant=\"small\" data-onclick=\"toggleSection('userPreferencesS",
            "pattern": "data-button-type",
            "match": "data-button-type"
          },
          {
            "line": 47,
            "content": "<div id=\"unified-header\"></div>",
            "pattern": "unified-header",
            "match": "unified-header"
          }
        ],
        "issue_count": 19
      }
    }
  }
}