{
  "session_info": {
    "session_id": 1,
    "user_id": 1,
    "created_at": {
      "utc": "2025-11-13T19:54:20.137874Z",
      "epochMs": 1763063660137,
      "local": "2025-11-13T19:54:20.137874+00:00",
      "timezone": "UTC",
      "display": "13/11/2025 19:54"
    },
    "report_version": "1.0"
  },
  "steps": {
    "file_upload": {
      "timestamp": {
        "utc": "2025-11-13T19:54:20.137921Z",
        "epochMs": 1763063660137,
        "local": "2025-11-13T19:54:20.137921+00:00",
        "timezone": "UTC",
        "display": "13/11/2025 19:54"
      },
      "data": {
        "file_name": "activity - 2024.csv",
        "provider": "IBKR",
        "connector_info": {
          "provider_name": "IBKR",
          "source_value": "ibkr_import",
          "class_name": "IBKRConnector",
          "supports_external_id": true,
          "supports_validation": true
        },
        "task_type": "executions"
      }
    }
  },
  "summary": {
    "current_step": "file_upload",
    "total_steps": 6,
    "progress_percentage": 16.666666666666664
  }
}