{
  "timestamp": "2026-01-02T15:58:12.430Z",
  "pages": [
    {
      "file": "index.js",
      "totalFunctions": 28,
      "functionsWithCoverage": 7,
      "functionsWithoutCoverage": 21,
      "coveragePercentage": "25.00",
      "functions": [
        {
          "name": "toNumber",
          "hasTryCatch": false
        },
        {
          "name": "resolveDateValue",
          "hasTryCatch": false
        },
        {
          "name": "formatDateShort",
          "hasTryCatch": true
        },
        {
          "name": "normalizeArray",
          "hasTryCatch": false
        },
        {
          "name": "determineCurrencySymbol",
          "hasTryCatch": false
        },
        {
          "name": "computePortfolioPnL",
          "hasTryCatch": false
        },
        {
          "name": "updateSummaryStats",
          "hasTryCatch": false
        },
        {
          "name": "updateRecentItemsWidget",
          "hasTryCatch": false
        },
        {
          "name": "updateRecentTradePlans",
          "hasTryCatch": false
        },
        {
          "name": "updateRecentTrades",
          "hasTryCatch": false
        },
        {
          "name": "updateActiveAlerts",
          "hasTryCatch": false
        },
        {
          "name": "updateDashboardCount",
          "hasTryCatch": false
        },
        {
          "name": "updatePortfolioSummary",
          "hasTryCatch": false
        },
        {
          "name": "showDashboardError",
          "hasTryCatch": false
        },
        {
          "name": "handleDashboardError",
          "hasTryCatch": false
        },
        {
          "name": "processDashboardData",
          "hasTryCatch": false
        },
        {
          "name": "loadRecentTradePlans",
          "hasTryCatch": true
        },
        {
          "name": "legacyFetchDashboardDataFromApi",
          "hasTryCatch": false
        },
        {
          "name": "loadDashboardDataFromService",
          "hasTryCatch": false
        },
        {
          "name": "switchTableTab",
          "hasTryCatch": false
        },
        {
          "name": "refreshOverview",
          "hasTryCatch": true
        },
        {
          "name": "exportOverview",
          "hasTryCatch": false
        },
        {
          "name": "quickAction",
          "hasTryCatch": false
        },
        {
          "name": "replaceIconsWithIconSystem",
          "hasTryCatch": true
        },
        {
          "name": "generateDetailedLog",
          "hasTryCatch": true
        },
        {
          "name": "debugZIndexStatus",
          "hasTryCatch": false
        },
        {
          "name": "copyDetailedLogLocal",
          "hasTryCatch": true
        },
        {
          "name": "equalizeWidgetHeights",
          "hasTryCatch": true
        }
      ]
    },
    {
      "file": "trades.js",
      "totalFunctions": 83,
      "functionsWithCoverage": 58,
      "functionsWithoutCoverage": 25,
      "coveragePercentage": "69.88",
      "functions": [
        {
          "name": "formatDailyChange",
          "hasTryCatch": true
        },
        {
          "name": "getInvestmentTypeColor",
          "hasTryCatch": true
        },
        {
          "name": "loadTradesData",
          "hasTryCatch": true
        },
        {
          "name": "syncTradesPagination",
          "hasTryCatch": true
        },
        {
          "name": "updateTradesSummary",
          "hasTryCatch": true
        },
        {
          "name": "updateTradesCounters",
          "hasTryCatch": true
        },
        {
          "name": "setTradesFilteredDataset",
          "hasTryCatch": true
        },
        {
          "name": "getTradesPaginationOptions",
          "hasTryCatch": false
        },
        {
          "name": "handleTradesPageRender",
          "hasTryCatch": false
        },
        {
          "name": "handleTradesFilteredChange",
          "hasTryCatch": false
        },
        {
          "name": "loadTradeTickerInfo",
          "hasTryCatch": true
        },
        {
          "name": "displayTradeTickerInfo",
          "hasTryCatch": false
        },
        {
          "name": "loadTickerDataForTrades",
          "hasTryCatch": true
        },
        {
          "name": "updateTradesTable",
          "hasTryCatch": true
        },
        {
          "name": "loadTradePlanDates",
          "hasTryCatch": true
        },
        {
          "name": "viewTickerDetails",
          "hasTryCatch": true
        },
        {
          "name": "viewAccountDetails",
          "hasTryCatch": true
        },
        {
          "name": "viewTradePlanDetails",
          "hasTryCatch": true
        },
        {
          "name": "editTradeRecord",
          "hasTryCatch": true
        },
        {
          "name": "cancelTradeRecord",
          "hasTryCatch": true
        },
        {
          "name": "performTradeCancellation",
          "hasTryCatch": true
        },
        {
          "name": "deleteTradeRecord",
          "hasTryCatch": true
        },
        {
          "name": "performTradeDeletion",
          "hasTryCatch": true
        },
        {
          "name": "addEditImportantNote",
          "hasTryCatch": true
        },
        {
          "name": "addEditReminder",
          "hasTryCatch": true
        },
        {
          "name": "restorePageState",
          "hasTryCatch": true
        },
        {
          "name": "addTrade",
          "hasTryCatch": false
        },
        {
          "name": "editTrade",
          "hasTryCatch": false
        },
        {
          "name": "clearTradeValidation",
          "hasTryCatch": false
        },
        {
          "name": "validateTradeForm",
          "hasTryCatch": false
        },
        {
          "name": "hideAddTradeModal",
          "hasTryCatch": true
        },
        {
          "name": "hideEditTradeModal",
          "hasTryCatch": true
        },
        {
          "name": "updateRadioButtons",
          "hasTryCatch": true
        },
        {
          "name": "populateSelect",
          "hasTryCatch": true
        },
        {
          "name": "onRelationTypeChange",
          "hasTryCatch": true
        },
        {
          "name": "onRelatedObjectChange",
          "hasTryCatch": true
        },
        {
          "name": "enableConditionFields",
          "hasTryCatch": true
        },
        {
          "name": "disableConditionFields",
          "hasTryCatch": true
        },
        {
          "name": "populateRelatedObjects",
          "hasTryCatch": true
        },
        {
          "name": "restoreSortState",
          "hasTryCatch": true
        },
        {
          "name": "enableTradeFormFields",
          "hasTryCatch": true
        },
        {
          "name": "disableTradeFormFields",
          "hasTryCatch": true
        },
        {
          "name": "loadModalData",
          "hasTryCatch": true
        },
        {
          "name": "initializeTradesPage",
          "hasTryCatch": true
        },
        {
          "name": "refreshPositions",
          "hasTryCatch": true
        },
        {
          "name": "setupDateValidation",
          "hasTryCatch": true
        },
        {
          "name": "validateDateFields",
          "hasTryCatch": true
        },
        {
          "name": "clearDateValidationMessages",
          "hasTryCatch": true
        },
        {
          "name": "addImportantNote",
          "hasTryCatch": false
        },
        {
          "name": "addReminder",
          "hasTryCatch": false
        },
        {
          "name": "onShowClosedTradesChange",
          "hasTryCatch": true
        },
        {
          "name": "updateTableStats",
          "hasTryCatch": true
        },
        {
          "name": "addEditBuySell",
          "hasTryCatch": true
        },
        {
          "name": "initializeTradeConditionsSystem",
          "hasTryCatch": true
        },
        {
          "name": "getTradesModalElement",
          "hasTryCatch": false
        },
        {
          "name": "getTradeModalEntityName",
          "hasTryCatch": false
        },
        {
          "name": "openTradeConditionsModal",
          "hasTryCatch": false
        },
        {
          "name": "handleTradeConditionsButtonClick",
          "hasTryCatch": false
        },
        {
          "name": "handleTradeConditionSummaryEdit",
          "hasTryCatch": false
        },
        {
          "name": "handleTradeConditionSummaryDelete",
          "hasTryCatch": false
        },
        {
          "name": "evaluateSingleTradeCondition",
          "hasTryCatch": false
        },
        {
          "name": "handleTradeConditionRowEvaluate",
          "hasTryCatch": true
        },
        {
          "name": "handleTradeConditionToggleAlerts",
          "hasTryCatch": true
        },
        {
          "name": "handleTradeEvaluateConditionsClick",
          "hasTryCatch": true
        },
        {
          "name": "getTradeConditionsForEvaluation",
          "hasTryCatch": false
        },
        {
          "name": "loadTradeConditionsSummary",
          "hasTryCatch": false
        },
        {
          "name": "setupTradeConditionsButton",
          "hasTryCatch": false
        },
        {
          "name": "setupSortEventListeners",
          "hasTryCatch": false
        },
        {
          "name": "validateTradePlanChange",
          "hasTryCatch": false
        },
        {
          "name": "validateTradeChanges",
          "hasTryCatch": true
        },
        {
          "name": "applyStatusFilterToTrades",
          "hasTryCatch": true
        },
        {
          "name": "validateTickerChange",
          "hasTryCatch": false
        },
        {
          "name": "showTickerChangeConfirmation",
          "hasTryCatch": true
        },
        {
          "name": "validateTradePlanDate",
          "hasTryCatch": false
        },
        {
          "name": "updateEditTradeTickerFromPlan",
          "hasTryCatch": true
        },
        {
          "name": "updateEditTradePriceFromTicker",
          "hasTryCatch": true
        },
        {
          "name": "reactivateTrade",
          "hasTryCatch": true
        },
        {
          "name": "refreshTrades",
          "hasTryCatch": true
        },
        {
          "name": "updateTrade",
          "hasTryCatch": true
        },
        {
          "name": "confirmDeleteTrade",
          "hasTryCatch": true
        },
        {
          "name": "generateDetailedLog",
          "hasTryCatch": true
        },
        {
          "name": "deleteTrade",
          "hasTryCatch": false
        },
        {
          "name": "setupTradeConditionsButton",
          "hasTryCatch": true
        }
      ]
    },
    {
      "file": "executions.js",
      "totalFunctions": 88,
      "functionsWithCoverage": 44,
      "functionsWithoutCoverage": 44,
      "coveragePercentage": "50.00",
      "functions": [
        {
          "name": "addExecution",
          "hasTryCatch": true
        },
        {
          "name": "editExecution",
          "hasTryCatch": true
        },
        {
          "name": "updateRealizedPLField",
          "hasTryCatch": false
        },
        {
          "name": "saveExecution",
          "hasTryCatch": true
        },
        {
          "name": "updateExecution",
          "hasTryCatch": false
        },
        {
          "name": "displayLinkedItems",
          "hasTryCatch": true
        },
        {
          "name": "goToTrade",
          "hasTryCatch": true
        },
        {
          "name": "goToPlan",
          "hasTryCatch": true
        },
        {
          "name": "goToAlert",
          "hasTryCatch": true
        },
        {
          "name": "goToNote",
          "hasTryCatch": true
        },
        {
          "name": "loadExecutionsData",
          "hasTryCatch": false
        },
        {
          "name": "syncExecutionsPagination",
          "hasTryCatch": true
        },
        {
          "name": "setExecutionsFilteredDataset",
          "hasTryCatch": true
        },
        {
          "name": "getExecutionsPaginationOptions",
          "hasTryCatch": false
        },
        {
          "name": "handleExecutionsPageRender",
          "hasTryCatch": false
        },
        {
          "name": "handleExecutionsFilteredChange",
          "hasTryCatch": false
        },
        {
          "name": "applyExecutionsFilteredData",
          "hasTryCatch": false
        },
        {
          "name": "updateExecutionsSummary",
          "hasTryCatch": true
        },
        {
          "name": "updateExecutionsCounters",
          "hasTryCatch": true
        },
        {
          "name": "updateExecutionsTableMain",
          "hasTryCatch": false
        },
        {
          "name": "isDateInRange",
          "hasTryCatch": true
        },
        {
          "name": "filterExecutionsLocally",
          "hasTryCatch": true
        },
        {
          "name": "restoreSortState",
          "hasTryCatch": true
        },
        {
          "name": "loadAndRenderClusters",
          "hasTryCatch": false
        },
        {
          "name": "renderClusters",
          "hasTryCatch": false
        },
        {
          "name": "handleClusterCheckboxChange",
          "hasTryCatch": false
        },
        {
          "name": "updateClusterSummary",
          "hasTryCatch": false
        },
        {
          "name": "handleClusterButtonClick",
          "hasTryCatch": false
        },
        {
          "name": "preloadSections34Data",
          "hasTryCatch": true
        },
        {
          "name": "setupModalConfigurations",
          "hasTryCatch": true
        },
        {
          "name": "loadTickersWithOpenOrClosedTradesAndPlans",
          "hasTryCatch": true
        },
        {
          "name": "enableAllFields",
          "hasTryCatch": true
        },
        {
          "name": "loadActiveTradesForTicker",
          "hasTryCatch": true
        },
        {
          "name": "updateTradesOnCheckboxChange",
          "hasTryCatch": true
        },
        {
          "name": "updateTradesOnTickerChange",
          "hasTryCatch": true
        },
        {
          "name": "goToTickerPage",
          "hasTryCatch": true
        },
        {
          "name": "showTickerHelp",
          "hasTryCatch": true
        },
        {
          "name": "addNewTicker",
          "hasTryCatch": true
        },
        {
          "name": "addNewPlan",
          "hasTryCatch": true
        },
        {
          "name": "addNewTrade",
          "hasTryCatch": true
        },
        {
          "name": "toggleExecutionFormFields",
          "hasTryCatch": false
        },
        {
          "name": "enableExecutionFormFields",
          "hasTryCatch": false
        },
        {
          "name": "disableExecutionFormFields",
          "hasTryCatch": false
        },
        {
          "name": "loadExecutionTickerInfo",
          "hasTryCatch": true
        },
        {
          "name": "displayExecutionTickerInfo",
          "hasTryCatch": false
        },
        {
          "name": "hideExecutionTickerInfo",
          "hasTryCatch": false
        },
        {
          "name": "calculateExecutionValues",
          "hasTryCatch": true
        },
        {
          "name": "calculateAddExecutionValues",
          "hasTryCatch": false
        },
        {
          "name": "calculateEditExecutionValues",
          "hasTryCatch": false
        },
        {
          "name": "setupExecutionCalculationListeners",
          "hasTryCatch": true
        },
        {
          "name": "setupEditExecutionCalculationListeners",
          "hasTryCatch": true
        },
        {
          "name": "goToLinkedTrade",
          "hasTryCatch": false
        },
        {
          "name": "loadTradeExecutions",
          "hasTryCatch": true
        },
        {
          "name": "updateExecutionsTableForTradeModal",
          "hasTryCatch": false
        },
        {
          "name": "addEditBuySell",
          "hasTryCatch": false
        },
        {
          "name": "linkExistingExecution",
          "hasTryCatch": false
        },
        {
          "name": "unlinkExecution",
          "hasTryCatch": false
        },
        {
          "name": "setupExecutionsFilterFunctions",
          "hasTryCatch": true
        },
        {
          "name": "applyAccountFilterWithTradesData",
          "hasTryCatch": false
        },
        {
          "name": "updateExecutionsGlobalData",
          "hasTryCatch": false
        },
        {
          "name": "toggleExternalIdField",
          "hasTryCatch": false
        },
        {
          "name": "loadTickersSummaryData",
          "hasTryCatch": true
        },
        {
          "name": "updateTickersSummaryTable",
          "hasTryCatch": false
        },
        {
          "name": "refreshTickersSummary",
          "hasTryCatch": false
        },
        {
          "name": "viewTickerDetails",
          "hasTryCatch": false
        },
        {
          "name": "addExecutionForTicker",
          "hasTryCatch": false
        },
        {
          "name": "updateTickersList",
          "hasTryCatch": true
        },
        {
          "name": "deleteExecution",
          "hasTryCatch": true
        },
        {
          "name": "performExecutionDeletion",
          "hasTryCatch": true
        },
        {
          "name": "restorePageState",
          "hasTryCatch": true
        },
        {
          "name": "loadTradeSuggestionsForAll",
          "hasTryCatch": true
        },
        {
          "name": "updateSuggestionsCount",
          "hasTryCatch": false
        },
        {
          "name": "renderTradeSuggestionsSection",
          "hasTryCatch": false
        },
        {
          "name": "buildTradeSuggestionRow",
          "hasTryCatch": false
        },
        {
          "name": "toggleAllSuggestions",
          "hasTryCatch": false
        },
        {
          "name": "acceptSuggestion",
          "hasTryCatch": true
        },
        {
          "name": "rejectSuggestion",
          "hasTryCatch": true
        },
        {
          "name": "acceptAllSuggestions",
          "hasTryCatch": true
        },
        {
          "name": "rejectAllSuggestions",
          "hasTryCatch": false
        },
        {
          "name": "applySelectedSuggestions",
          "hasTryCatch": true
        },
        {
          "name": "openTradeDetailsModal",
          "hasTryCatch": false
        },
        {
          "name": "getTradeSuggestionsFlatData",
          "hasTryCatch": false
        },
        {
          "name": "sortTradeSuggestionsTable",
          "hasTryCatch": false
        },
        {
          "name": "updateTradeSuggestionsTable",
          "hasTryCatch": false
        },
        {
          "name": "initializeTradeSuggestionsPagination",
          "hasTryCatch": false
        },
        {
          "name": "renderTradeSuggestionsPageRows",
          "hasTryCatch": false
        },
        {
          "name": "buildTradeSuggestionsFlatList",
          "hasTryCatch": false
        },
        {
          "name": "loadEODExecutionsData",
          "hasTryCatch": true
        }
      ]
    },
    {
      "file": "alerts.js",
      "totalFunctions": 55,
      "functionsWithCoverage": 30,
      "functionsWithoutCoverage": 25,
      "coveragePercentage": "54.55",
      "functions": [
        {
          "name": "loadAlertsDataInternal",
          "hasTryCatch": false
        },
        {
          "name": "getConditionSourceDisplay",
          "hasTryCatch": true
        },
        {
          "name": "renderAlertsTableRows",
          "hasTryCatch": true
        },
        {
          "name": "updateAlertsTable",
          "hasTryCatch": false
        },
        {
          "name": "loadModalData",
          "hasTryCatch": true
        },
        {
          "name": "updateRadioButtons",
          "hasTryCatch": true
        },
        {
          "name": "populateSelect",
          "hasTryCatch": true
        },
        {
          "name": "onRelationTypeChange",
          "hasTryCatch": true
        },
        {
          "name": "onRelatedObjectChange",
          "hasTryCatch": true
        },
        {
          "name": "toggleConditionFields",
          "hasTryCatch": true
        },
        {
          "name": "enableConditionFields",
          "hasTryCatch": false
        },
        {
          "name": "disableConditionFields",
          "hasTryCatch": false
        },
        {
          "name": "enableEditConditionFields",
          "hasTryCatch": false
        },
        {
          "name": "disableEditConditionFields",
          "hasTryCatch": false
        },
        {
          "name": "populateRelatedObjects",
          "hasTryCatch": true
        },
        {
          "name": "parseAlertCondition",
          "hasTryCatch": true
        },
        {
          "name": "saveAlert",
          "hasTryCatch": true
        },
        {
          "name": "editAlert",
          "hasTryCatch": false
        },
        {
          "name": "getAlertState",
          "hasTryCatch": true
        },
        {
          "name": "validateAlertStatusCombination",
          "hasTryCatch": false
        },
        {
          "name": "updateStatusAndTriggered",
          "hasTryCatch": false
        },
        {
          "name": "updateAlert",
          "hasTryCatch": true
        },
        {
          "name": "deleteAlertInternal",
          "hasTryCatch": false
        },
        {
          "name": "confirmDeleteAlert",
          "hasTryCatch": true
        },
        {
          "name": "restoreAlertsSectionState",
          "hasTryCatch": false
        },
        {
          "name": "filterAlertsByRelatedObjectTypeWrapper",
          "hasTryCatch": false
        },
        {
          "name": "filterAlertsByRelatedObjectType",
          "hasTryCatch": true
        },
        {
          "name": "loadAlerts",
          "hasTryCatch": false
        },
        {
          "name": "reactivateAlert",
          "hasTryCatch": true
        },
        {
          "name": "updateAlertStatus",
          "hasTryCatch": true
        },
        {
          "name": "validateAlertForm",
          "hasTryCatch": true
        },
        {
          "name": "updateEvaluationStats",
          "hasTryCatch": true
        },
        {
          "name": "saveAlertData",
          "hasTryCatch": true
        },
        {
          "name": "generateDetailedLog",
          "hasTryCatch": false
        },
        {
          "name": "updateAlertsSummary",
          "hasTryCatch": false
        },
        {
          "name": "generateDetailedLogForAlerts",
          "hasTryCatch": true
        },
        {
          "name": "loadConditionsFromSource",
          "hasTryCatch": false
        },
        {
          "name": "loadTradePlansForConditions",
          "hasTryCatch": true
        },
        {
          "name": "loadTradesForConditions",
          "hasTryCatch": true
        },
        {
          "name": "loadConditionsFromItem",
          "hasTryCatch": true
        },
        {
          "name": "displayAvailableConditions",
          "hasTryCatch": false
        },
        {
          "name": "selectConditionForAlert",
          "hasTryCatch": false
        },
        {
          "name": "createAlertFromCondition",
          "hasTryCatch": true
        },
        {
          "name": "initializeAlertModalTabs",
          "hasTryCatch": false
        },
        {
          "name": "updateModalButtons",
          "hasTryCatch": false
        },
        {
          "name": "evaluateAllConditions",
          "hasTryCatch": true
        },
        {
          "name": "refreshConditionEvaluations",
          "hasTryCatch": true
        },
        {
          "name": "showEvaluationLoading",
          "hasTryCatch": false
        },
        {
          "name": "displayEvaluationResults",
          "hasTryCatch": false
        },
        {
          "name": "updateEvaluationSummary",
          "hasTryCatch": false
        },
        {
          "name": "loadAlertTickerInfo",
          "hasTryCatch": true
        },
        {
          "name": "displayAlertTickerInfo",
          "hasTryCatch": false
        },
        {
          "name": "clearAlertTickerInfo",
          "hasTryCatch": false
        },
        {
          "name": "restorePageState",
          "hasTryCatch": true
        },
        {
          "name": "loadEODAlertsData",
          "hasTryCatch": true
        }
      ]
    },
    {
      "file": "trade_plans.js",
      "totalFunctions": 72,
      "functionsWithCoverage": 39,
      "functionsWithoutCoverage": 33,
      "coveragePercentage": "54.17",
      "functions": [
        {
          "name": "executeTradePlan",
          "hasTryCatch": true
        },
        {
          "name": "loadTradePlanTickerInfo",
          "hasTryCatch": true
        },
        {
          "name": "displayTradePlanTickerInfo",
          "hasTryCatch": false
        },
        {
          "name": "hideTickerInfo",
          "hasTryCatch": true
        },
        {
          "name": "updateTickerInfo",
          "hasTryCatch": true
        },
        {
          "name": "updateSharesFromAmount",
          "hasTryCatch": true
        },
        {
          "name": "updateAmountFromShares",
          "hasTryCatch": true
        },
        {
          "name": "hideEditTickerInfo",
          "hasTryCatch": true
        },
        {
          "name": "updateEditTickerInfo",
          "hasTryCatch": false
        },
        {
          "name": "updateEditSharesFromAmount",
          "hasTryCatch": true
        },
        {
          "name": "updateEditAmountFromShares",
          "hasTryCatch": true
        },
        {
          "name": "checkLinkedItemsBeforeCancel",
          "hasTryCatch": false
        },
        {
          "name": "reactivateTradePlan",
          "hasTryCatch": true
        },
        {
          "name": "addEditCondition",
          "hasTryCatch": true
        },
        {
          "name": "addEditReason",
          "hasTryCatch": true
        },
        {
          "name": "addEditImportantNote",
          "hasTryCatch": true
        },
        {
          "name": "addEditReminder",
          "hasTryCatch": true
        },
        {
          "name": "addImportantNote",
          "hasTryCatch": true
        },
        {
          "name": "addReminder",
          "hasTryCatch": true
        },
        {
          "name": "buildTradePlanConfirmationDetails",
          "hasTryCatch": false
        },
        {
          "name": "openCancelTradePlanModal",
          "hasTryCatch": true
        },
        {
          "name": "cancelTradePlan",
          "hasTryCatch": true
        },
        {
          "name": "performTradePlanCancellation",
          "hasTryCatch": true
        },
        {
          "name": "viewLinkedItemsForTradePlan",
          "hasTryCatch": false
        },
        {
          "name": "updatePricesFromPercentages",
          "hasTryCatch": false
        },
        {
          "name": "updatePercentagesFromPrices",
          "hasTryCatch": false
        },
        {
          "name": "setupPriceCalculation",
          "hasTryCatch": true
        },
        {
          "name": "setupEditPriceCalculation",
          "hasTryCatch": true
        },
        {
          "name": "applyTradePlanDefaultRiskLevels",
          "hasTryCatch": false
        },
        {
          "name": "getTradePlanModalElements",
          "hasTryCatch": false
        },
        {
          "name": "parseFieldValue",
          "hasTryCatch": false
        },
        {
          "name": "parsePriceValue",
          "hasTryCatch": false
        },
        {
          "name": "normalizeSharesResult",
          "hasTryCatch": false
        },
        {
          "name": "loadTradePlansData",
          "hasTryCatch": true
        },
        {
          "name": "renderTradePlansTableRows",
          "hasTryCatch": true
        },
        {
          "name": "updateTradePlansTable",
          "hasTryCatch": false
        },
        {
          "name": "updateTradePlansPageSummaryStats",
          "hasTryCatch": true
        },
        {
          "name": "disableFormFields",
          "hasTryCatch": true
        },
        {
          "name": "enableEditFieldsWrapper",
          "hasTryCatch": true
        },
        {
          "name": "disableEditFields",
          "hasTryCatch": true
        },
        {
          "name": "getTradePlanModalEntityName",
          "hasTryCatch": false
        },
        {
          "name": "getTradePlansModalElement",
          "hasTryCatch": false
        },
        {
          "name": "isConditionsModalOpen",
          "hasTryCatch": false
        },
        {
          "name": "getCachedConditionSummary",
          "hasTryCatch": false
        },
        {
          "name": "clearCachedConditionsSummary",
          "hasTryCatch": false
        },
        {
          "name": "openTradePlanConditionsModal",
          "hasTryCatch": false
        },
        {
          "name": "handleTradePlanConditionsButtonClick",
          "hasTryCatch": false
        },
        {
          "name": "handleTradePlanConditionSummaryEdit",
          "hasTryCatch": false
        },
        {
          "name": "handleTradePlanConditionSummaryDelete",
          "hasTryCatch": false
        },
        {
          "name": "confirmTradePlanConditionDeletion",
          "hasTryCatch": false
        },
        {
          "name": "deleteConditionViaCrud",
          "hasTryCatch": true
        },
        {
          "name": "buildTradePlanModalNavigationMetadata",
          "hasTryCatch": false
        },
        {
          "name": "registerTradePlanModalNavigation",
          "hasTryCatch": true
        },
        {
          "name": "updateTradePlanModalNavigation",
          "hasTryCatch": false
        },
        {
          "name": "handleTradePlanModalRestore",
          "hasTryCatch": false
        },
        {
          "name": "setupTradePlanModalNavigation",
          "hasTryCatch": false
        },
        {
          "name": "getConditionsTranslator",
          "hasTryCatch": false
        },
        {
          "name": "handleTradePlanEvaluateConditionsClick",
          "hasTryCatch": true
        },
        {
          "name": "getTradePlanConditionsForEvaluation",
          "hasTryCatch": true
        },
        {
          "name": "evaluatePlanConditions",
          "hasTryCatch": false
        },
        {
          "name": "evaluateSinglePlanCondition",
          "hasTryCatch": false
        },
        {
          "name": "handleTradePlanConditionRowEvaluate",
          "hasTryCatch": true
        },
        {
          "name": "handleTradePlanConditionToggleAlerts",
          "hasTryCatch": true
        },
        {
          "name": "normalizeConditionEvaluationPayload",
          "hasTryCatch": false
        },
        {
          "name": "loadTradePlanConditionsSummary",
          "hasTryCatch": false
        },
        {
          "name": "setupTradePlanConditionsButton",
          "hasTryCatch": false
        },
        {
          "name": "restorePlanningSectionState",
          "hasTryCatch": true
        },
        {
          "name": "filterTradePlansByType",
          "hasTryCatch": true
        },
        {
          "name": "saveTradePlan",
          "hasTryCatch": true
        },
        {
          "name": "deleteTradePlan",
          "hasTryCatch": true
        },
        {
          "name": "performTradePlanDeletion",
          "hasTryCatch": true
        },
        {
          "name": "restorePageState",
          "hasTryCatch": true
        }
      ]
    },
    {
      "file": "cash_flows.js",
      "totalFunctions": 61,
      "functionsWithCoverage": 30,
      "functionsWithoutCoverage": 31,
      "coveragePercentage": "49.18",
      "functions": [
        {
          "name": "loadCashFlowsData",
          "hasTryCatch": false
        },
        {
          "name": "applyFallbackDateSort",
          "hasTryCatch": true
        },
        {
          "name": "calculateBalance",
          "hasTryCatch": true
        },
        {
          "name": "resolveExchangeDirectionFromType",
          "hasTryCatch": false
        },
        {
          "name": "getCashFlowsPaginationInstance",
          "hasTryCatch": false
        },
        {
          "name": "setActiveCashFlowTypeButton",
          "hasTryCatch": false
        },
        {
          "name": "setupCashFlowTypeFilterDropdown",
          "hasTryCatch": false
        },
        {
          "name": "cashFlowMatchesType",
          "hasTryCatch": false
        },
        {
          "name": "filterCashFlowsByType",
          "hasTryCatch": false
        },
        {
          "name": "filterCashFlowsLocallyByType",
          "hasTryCatch": false
        },
        {
          "name": "saveCashFlowTypeFilterState",
          "hasTryCatch": true
        },
        {
          "name": "loadCashFlowTypeFilterState",
          "hasTryCatch": true
        },
        {
          "name": "reapplyCashFlowTypeFilter",
          "hasTryCatch": false
        },
        {
          "name": "getAccountNameById",
          "hasTryCatch": true
        },
        {
          "name": "ensureTradingAccountsLoaded",
          "hasTryCatch": false
        },
        {
          "name": "validateCashFlowAmount",
          "hasTryCatch": false
        },
        {
          "name": "validateCashFlowDate",
          "hasTryCatch": false
        },
        {
          "name": "validateCashFlowForm",
          "hasTryCatch": true
        },
        {
          "name": "validateEditCashFlowForm",
          "hasTryCatch": true
        },
        {
          "name": "deleteCashFlow",
          "hasTryCatch": true
        },
        {
          "name": "performCashFlowDeletion",
          "hasTryCatch": true
        },
        {
          "name": "deleteImportedCashFlows",
          "hasTryCatch": true
        },
        {
          "name": "loadAccountsForCashFlow",
          "hasTryCatch": true
        },
        {
          "name": "loadCurrenciesForCashFlow",
          "hasTryCatch": true
        },
        {
          "name": "renderCashFlowsTable",
          "hasTryCatch": true
        },
        {
          "name": "updatePageSummaryStats",
          "hasTryCatch": true
        },
        {
          "name": "syncCashFlowsPagination",
          "hasTryCatch": true
        },
        {
          "name": "groupUnifiedExchanges",
          "hasTryCatch": false
        },
        {
          "name": "renderUnifiedForexExchangesTable",
          "hasTryCatch": true
        },
        {
          "name": "ensureExchangePairsAdjacency",
          "hasTryCatch": false
        },
        {
          "name": "setupExchangeRowInteractions",
          "hasTryCatch": false
        },
        {
          "name": "highlightExchangeGroup",
          "hasTryCatch": false
        },
        {
          "name": "clearExchangeHighlight",
          "hasTryCatch": false
        },
        {
          "name": "setCurrencyExchangeSummary",
          "hasTryCatch": false
        },
        {
          "name": "hydrateCashFlowExchangeDisplay",
          "hasTryCatch": false
        },
        {
          "name": "formatAmount",
          "hasTryCatch": true
        },
        {
          "name": "getCashFlowTypeWithColor",
          "hasTryCatch": true
        },
        {
          "name": "getCashFlowTypeText",
          "hasTryCatch": false
        },
        {
          "name": "resolveCurrencySymbolForCashFlow",
          "hasTryCatch": true
        },
        {
          "name": "formatCashFlowAmount",
          "hasTryCatch": false
        },
        {
          "name": "formatUsdRate",
          "hasTryCatch": false
        },
        {
          "name": "showCashFlowDetails",
          "hasTryCatch": false
        },
        {
          "name": "updateCashFlowsTable",
          "hasTryCatch": false
        },
        {
          "name": "startAutoRefresh",
          "hasTryCatch": true
        },
        {
          "name": "applyDynamicColors",
          "hasTryCatch": true
        },
        {
          "name": "applyUserPreferences",
          "hasTryCatch": true
        },
        {
          "name": "initializeCashFlowsPage",
          "hasTryCatch": true
        },
        {
          "name": "updateCashFlow",
          "hasTryCatch": true
        },
        {
          "name": "saveCashFlow",
          "hasTryCatch": true
        },
        {
          "name": "saveCurrencyExchange",
          "hasTryCatch": true
        },
        {
          "name": "loadCurrencyExchange",
          "hasTryCatch": true
        },
        {
          "name": "deleteCurrencyExchange",
          "hasTryCatch": true
        },
        {
          "name": "isCurrencyExchange",
          "hasTryCatch": false
        },
        {
          "name": "getExchangeIdFromCashFlow",
          "hasTryCatch": false
        },
        {
          "name": "confirmDeleteCashFlow",
          "hasTryCatch": false
        },
        {
          "name": "manageExternalIdField",
          "hasTryCatch": false
        },
        {
          "name": "setupSourceFieldListeners",
          "hasTryCatch": false
        },
        {
          "name": "initializeExternalIdFields",
          "hasTryCatch": false
        },
        {
          "name": "editCashFlow",
          "hasTryCatch": true
        },
        {
          "name": "generateDetailedLog",
          "hasTryCatch": false
        },
        {
          "name": "restorePageState",
          "hasTryCatch": true
        }
      ]
    },
    {
      "file": "notes.js",
      "totalFunctions": 38,
      "functionsWithCoverage": 31,
      "functionsWithoutCoverage": 7,
      "coveragePercentage": "81.58",
      "functions": [
        {
          "name": "loadAdditionalNotesData",
          "hasTryCatch": true
        },
        {
          "name": "downloadFile",
          "hasTryCatch": true
        },
        {
          "name": "openNoteDetails",
          "hasTryCatch": true
        },
        {
          "name": "editNote",
          "hasTryCatch": false
        },
        {
          "name": "deleteNote",
          "hasTryCatch": true
        },
        {
          "name": "updateNotesTable",
          "hasTryCatch": false
        },
        {
          "name": "updateNotesSummary",
          "hasTryCatch": true
        },
        {
          "name": "updateGridFromComponent",
          "hasTryCatch": true
        },
        {
          "name": "populateSelect",
          "hasTryCatch": true
        },
        {
          "name": "updateRadioButtons",
          "hasTryCatch": true
        },
        {
          "name": "onNoteRelationTypeChange",
          "hasTryCatch": false
        },
        {
          "name": "populateEditSelectByType",
          "hasTryCatch": true
        },
        {
          "name": "populateEditSelectByTypeFallback",
          "hasTryCatch": false
        },
        {
          "name": "validateNoteForm",
          "hasTryCatch": false
        },
        {
          "name": "saveNote",
          "hasTryCatch": true
        },
        {
          "name": "updateNoteFromModal",
          "hasTryCatch": true
        },
        {
          "name": "confirmDeleteNote",
          "hasTryCatch": false
        },
        {
          "name": "deleteNoteFromServer",
          "hasTryCatch": true
        },
        {
          "name": "clearNoteValidationErrors",
          "hasTryCatch": true
        },
        {
          "name": "setupNoteValidationEvents",
          "hasTryCatch": true
        },
        {
          "name": "clearSelectedFile",
          "hasTryCatch": true
        },
        {
          "name": "restoreSortState",
          "hasTryCatch": true
        },
        {
          "name": "showTickerPage",
          "hasTryCatch": true
        },
        {
          "name": "formatText",
          "hasTryCatch": true
        },
        {
          "name": "clearFormatting",
          "hasTryCatch": true
        },
        {
          "name": "getEditorContent",
          "hasTryCatch": true
        },
        {
          "name": "setEditorContent",
          "hasTryCatch": true
        },
        {
          "name": "filterNotesData",
          "hasTryCatch": true
        },
        {
          "name": "filterNotesByType",
          "hasTryCatch": true
        },
        {
          "name": "getTypeDisplayName",
          "hasTryCatch": true
        },
        {
          "name": "viewNote",
          "hasTryCatch": true
        },
        {
          "name": "loadNoteForViewing",
          "hasTryCatch": true
        },
        {
          "name": "getNoteRelatedDisplay",
          "hasTryCatch": true
        },
        {
          "name": "editCurrentNote",
          "hasTryCatch": true
        },
        {
          "name": "displayCurrentAttachment",
          "hasTryCatch": true
        },
        {
          "name": "removeCurrentAttachment",
          "hasTryCatch": true
        },
        {
          "name": "replaceCurrentAttachment",
          "hasTryCatch": false
        },
        {
          "name": "restorePageState",
          "hasTryCatch": true
        }
      ]
    },
    {
      "file": "research.js",
      "totalFunctions": 7,
      "functionsWithCoverage": 1,
      "functionsWithoutCoverage": 6,
      "coveragePercentage": "14.29",
      "functions": [
        {
          "name": "getContainer",
          "hasTryCatch": false
        },
        {
          "name": "renderPlaceholder",
          "hasTryCatch": false
        },
        {
          "name": "renderDataState",
          "hasTryCatch": false
        },
        {
          "name": "loadResearchData",
          "hasTryCatch": false
        },
        {
          "name": "initializeResearchPage",
          "hasTryCatch": false
        },
        {
          "name": "loadEODResearchData",
          "hasTryCatch": false
        },
        {
          "name": "generateResearchInsights",
          "hasTryCatch": true
        }
      ]
    },
    {
      "file": "tickers.js",
      "totalFunctions": 53,
      "functionsWithCoverage": 36,
      "functionsWithoutCoverage": 17,
      "coveragePercentage": "67.92",
      "functions": [
        {
          "name": "editTicker",
          "hasTryCatch": false
        },
        {
          "name": "viewTickerDetails",
          "hasTryCatch": true
        },
        {
          "name": "loadCurrenciesData",
          "hasTryCatch": true
        },
        {
          "name": "getCurrencySymbol",
          "hasTryCatch": true
        },
        {
          "name": "getTickerTypeStyle",
          "hasTryCatch": true
        },
        {
          "name": "getTickerStatusStyle",
          "hasTryCatch": true
        },
        {
          "name": "getTickerStatusLabel",
          "hasTryCatch": true
        },
        {
          "name": "generateTickerCurrencyOptions",
          "hasTryCatch": true
        },
        {
          "name": "updateCurrencyOptions",
          "hasTryCatch": true
        },
        {
          "name": "updateActiveTradesField",
          "hasTryCatch": true
        },
        {
          "name": "updateTickerActiveTradesStatus",
          "hasTryCatch": true
        },
        {
          "name": "updateAllActiveTradesStatuses",
          "hasTryCatch": true
        },
        {
          "name": "restoreTickersSectionState",
          "hasTryCatch": true
        },
        {
          "name": "loadTickerProviderSymbols",
          "hasTryCatch": true
        },
        {
          "name": "initializeProviderSymbolFields",
          "hasTryCatch": false
        },
        {
          "name": "loadProviderSymbolFields",
          "hasTryCatch": true
        },
        {
          "name": "collectProviderSymbols",
          "hasTryCatch": false
        },
        {
          "name": "populateProviderSymbolFields",
          "hasTryCatch": false
        },
        {
          "name": "saveTicker",
          "hasTryCatch": true
        },
        {
          "name": "updateTicker",
          "hasTryCatch": true
        },
        {
          "name": "cancelTicker",
          "hasTryCatch": true
        },
        {
          "name": "checkLinkedItemsAndCancelTicker",
          "hasTryCatch": false
        },
        {
          "name": "performTickerCancellation",
          "hasTryCatch": true
        },
        {
          "name": "checkLinkedItemsBeforeDeleteTicker",
          "hasTryCatch": false
        },
        {
          "name": "checkLinkedItemsBeforeCancelTicker",
          "hasTryCatch": false
        },
        {
          "name": "getTickerSymbol",
          "hasTryCatch": true
        },
        {
          "name": "updateAllTickerStatuses",
          "hasTryCatch": true
        },
        {
          "name": "performCancelTicker",
          "hasTryCatch": true
        },
        {
          "name": "reactivateTicker",
          "hasTryCatch": true
        },
        {
          "name": "checkLinkedItemsAndDeleteTicker",
          "hasTryCatch": false
        },
        {
          "name": "performTickerDeletion",
          "hasTryCatch": true
        },
        {
          "name": "deleteTicker",
          "hasTryCatch": true
        },
        {
          "name": "confirmDeleteTicker",
          "hasTryCatch": true
        },
        {
          "name": "checkTickerDataCompleteness",
          "hasTryCatch": false
        },
        {
          "name": "checkTickersDataCompleteness",
          "hasTryCatch": false
        },
        {
          "name": "ensureHistoricalDataForTickers",
          "hasTryCatch": false
        },
        {
          "name": "enrichTickersWithFullData",
          "hasTryCatch": false
        },
        {
          "name": "loadAndRefreshMissingData",
          "hasTryCatch": false
        },
        {
          "name": "getDataStatusBadge",
          "hasTryCatch": false
        },
        {
          "name": "loadTickersDataInternal",
          "hasTryCatch": false
        },
        {
          "name": "updateTickersSummaryStats",
          "hasTryCatch": true
        },
        {
          "name": "renderTickersTableRows",
          "hasTryCatch": true
        },
        {
          "name": "updateTickersTable",
          "hasTryCatch": false
        },
        {
          "name": "checkTickerExternalData",
          "hasTryCatch": true
        },
        {
          "name": "restorePageState",
          "hasTryCatch": true
        },
        {
          "name": "loadColorsAndApplyToHeaders",
          "hasTryCatch": true
        },
        {
          "name": "tryLoadData",
          "hasTryCatch": false
        },
        {
          "name": "refreshTickerExternalData",
          "hasTryCatch": true
        },
        {
          "name": "refreshAllTickersData",
          "hasTryCatch": true
        },
        {
          "name": "refreshYahooFinanceData",
          "hasTryCatch": true
        },
        {
          "name": "refreshYahooFinanceDataSilently",
          "hasTryCatch": true
        },
        {
          "name": "filterTickersByType",
          "hasTryCatch": true
        },
        {
          "name": "getTypeDisplayName",
          "hasTryCatch": true
        }
      ]
    },
    {
      "file": "trading_accounts.js",
      "totalFunctions": 42,
      "functionsWithCoverage": 19,
      "functionsWithoutCoverage": 23,
      "coveragePercentage": "45.24",
      "functions": [
        {
          "name": "loadCurrenciesFromServer",
          "hasTryCatch": false
        },
        {
          "name": "generateCurrencyOptions",
          "hasTryCatch": false
        },
        {
          "name": "loadTradingAccountsFromServer",
          "hasTryCatch": false
        },
        {
          "name": "loadAllTradingAccountsFromServer",
          "hasTryCatch": false
        },
        {
          "name": "loadDefaultTradingAccounts",
          "hasTryCatch": true
        },
        {
          "name": "legacyFetchTradingAccounts",
          "hasTryCatch": false
        },
        {
          "name": "loadTradingAccountsData",
          "hasTryCatch": false
        },
        {
          "name": "loadAccountBalance",
          "hasTryCatch": true
        },
        {
          "name": "loadAccountBalancesBatch",
          "hasTryCatch": false
        },
        {
          "name": "getCurrencySymbol",
          "hasTryCatch": false
        },
        {
          "name": "enrichAccountsWithBalances",
          "hasTryCatch": false
        },
        {
          "name": "syncTradingAccountsPagination",
          "hasTryCatch": true
        },
        {
          "name": "updateTradingAccountsTable",
          "hasTryCatch": true
        },
        {
          "name": "updateTradingAccountsSummary",
          "hasTryCatch": true
        },
        {
          "name": "loadTradingAccounts",
          "hasTryCatch": true
        },
        {
          "name": "updateTradingAccountFilterDisplayText",
          "hasTryCatch": true
        },
        {
          "name": "deleteTradingAccountFromAPI",
          "hasTryCatch": true
        },
        {
          "name": "cancelTradingAccount",
          "hasTryCatch": true
        },
        {
          "name": "confirmDeleteTradingAccount",
          "hasTryCatch": false
        },
        {
          "name": "showOpenTradesWarning",
          "hasTryCatch": false
        },
        {
          "name": "showEditTradingAccountModalById",
          "hasTryCatch": false
        },
        {
          "name": "filterTradingAccountsLocally",
          "hasTryCatch": false
        },
        {
          "name": "updateTradingAccountFilterMenu",
          "hasTryCatch": false
        },
        {
          "name": "restoreTradingAccountsSectionState",
          "hasTryCatch": false
        },
        {
          "name": "cancelTradingAccountWithLinkedItemsCheck",
          "hasTryCatch": true
        },
        {
          "name": "deleteTradingAccountWithLinkedItemsCheck",
          "hasTryCatch": true
        },
        {
          "name": "restoreTradingAccount",
          "hasTryCatch": true
        },
        {
          "name": "checkLinkedItemsAndCancelTradingAccount",
          "hasTryCatch": false
        },
        {
          "name": "performTradingAccountCancellation",
          "hasTryCatch": true
        },
        {
          "name": "checkLinkedItemsAndDeleteTradingAccount",
          "hasTryCatch": false
        },
        {
          "name": "checkLinkedItemsBeforeCancelTradingAccount",
          "hasTryCatch": false
        },
        {
          "name": "checkLinkedItemsBeforeDeleteTradingAccount",
          "hasTryCatch": false
        },
        {
          "name": "getTradingAccountName",
          "hasTryCatch": false
        },
        {
          "name": "updateTradingAccount",
          "hasTryCatch": true
        },
        {
          "name": "showTradingAccountDetails",
          "hasTryCatch": true
        },
        {
          "name": "generateDetailedLog",
          "hasTryCatch": false
        },
        {
          "name": "getTradingAccounts",
          "hasTryCatch": false
        },
        {
          "name": "saveTradingAccount",
          "hasTryCatch": true
        },
        {
          "name": "deleteTradingAccount",
          "hasTryCatch": true
        },
        {
          "name": "performTradingAccountDeletion",
          "hasTryCatch": true
        },
        {
          "name": "restorePageState",
          "hasTryCatch": true
        },
        {
          "name": "waitAndRegisterTables",
          "hasTryCatch": false
        }
      ]
    },
    {
      "file": "database.js",
      "totalFunctions": 15,
      "functionsWithCoverage": 13,
      "functionsWithoutCoverage": 2,
      "coveragePercentage": "86.67",
      "functions": [
        {
          "name": "initDatabaseDisplay",
          "hasTryCatch": true
        },
        {
          "name": "setupEventListeners",
          "hasTryCatch": true
        },
        {
          "name": "loadTableData",
          "hasTryCatch": true
        },
        {
          "name": "fetchTableData",
          "hasTryCatch": false
        },
        {
          "name": "updateTableDisplay",
          "hasTryCatch": true
        },
        {
          "name": "createTableBodyHTML",
          "hasTryCatch": true
        },
        {
          "name": "formatCellValue",
          "hasTryCatch": true
        },
        {
          "name": "applySortingFunctionality",
          "hasTryCatch": true
        },
        {
          "name": "showLoadingState",
          "hasTryCatch": true
        },
        {
          "name": "updateTableInfo",
          "hasTryCatch": true
        },
        {
          "name": "filterTableData",
          "hasTryCatch": true
        },
        {
          "name": "formatNumber",
          "hasTryCatch": true
        },
        {
          "name": "formatCurrency",
          "hasTryCatch": true
        },
        {
          "name": "formatStatus",
          "hasTryCatch": true
        },
        {
          "name": "addRecord",
          "hasTryCatch": false
        }
      ]
    },
    {
      "file": "preferences-page.js",
      "totalFunctions": 9,
      "functionsWithCoverage": 8,
      "functionsWithoutCoverage": 1,
      "coveragePercentage": "88.89",
      "functions": [
        {
          "name": "loadAccountsForPreferences",
          "hasTryCatch": true
        },
        {
          "name": "switchActiveProfile",
          "hasTryCatch": true
        },
        {
          "name": "createNewProfile",
          "hasTryCatch": true
        },
        {
          "name": "copyDetailedLogLocal",
          "hasTryCatch": true
        },
        {
          "name": "initializePreferencesPage",
          "hasTryCatch": false
        },
        {
          "name": "deleteSelectedProfile",
          "hasTryCatch": true
        },
        {
          "name": "loadDeleteProfileDropdown",
          "hasTryCatch": true
        },
        {
          "name": "updateDeleteProfileButtonState",
          "hasTryCatch": true
        },
        {
          "name": "updatePreferencesSummary",
          "hasTryCatch": true
        }
      ]
    }
  ],
  "summary": {
    "total": 551,
    "withCoverage": 316,
    "withoutCoverage": 235,
    "coveragePercentage": "57.35"
  },
  "generatedAt": "2026-01-02T15:58:12.442Z",
  "version": "1.0.0"
}