{
  "start_time": "2025-11-22T13:56:28.258228",
  "steps": [
    {
      "number": 3,
      "name": "cleanup_documentation",
      "success": true,
      "duration_seconds": 0.02112269401550293,
      "timestamp": "2025-11-22T13:56:28.289010",
      "details": {
        "success": true,
        "removed_count": 0
      }
    },
    {
      "number": 4,
      "name": "backup_database",
      "success": true,
      "duration_seconds": 0.028636932373046875,
      "timestamp": "2025-11-22T13:56:28.318003",
      "details": {
        "success": true,
        "backup_file": "/Users/nimrod/Documents/TikTrack/TikTrackApp-Production/production/Backend/db/backups/tiktrack_pre-update_20251122_115628.db"
      }
    },
    {
      "number": 5,
      "name": "sync_code",
      "success": true,
      "duration_seconds": 0.5160231590270996,
      "timestamp": "2025-11-22T13:56:28.834377",
      "details": {
        "success": true
      }
    },
    {
      "number": 6,
      "name": "cleanup_backups",
      "success": true,
      "duration_seconds": 0.004971027374267578,
      "timestamp": "2025-11-22T13:56:28.839637",
      "details": {
        "success": true,
        "warning": "Cleanup had warnings"
      }
    },
    {
      "number": 7,
      "name": "fix_config",
      "success": true,
      "duration_seconds": 0.0008537769317626953,
      "timestamp": "2025-11-22T13:56:28.840763",
      "details": {
        "success": true,
        "verified": false,
        "warning": "Settings mismatch"
      }
    },
    {
      "number": 8,
      "name": "validate",
      "success": true,
      "duration_seconds": 0.18036484718322754,
      "timestamp": "2025-11-22T13:56:29.021331",
      "details": {
        "success": true,
        "results": {
          "isolation": false,
          "structure": false,
          "post_validation": false,
          "ui_tests": true
        }
      }
    },
    {
      "number": 9,
      "name": "bump_version",
      "success": true,
      "duration_seconds": 0.03373575210571289,
      "timestamp": "2025-11-22T13:56:29.055508",
      "details": {
        "success": true,
        "new_version": "1.2.4.0"
      }
    },
    {
      "number": 10,
      "name": "commit_push",
      "success": true,
      "duration_seconds": 1.8623852729797363,
      "timestamp": "2025-11-22T13:56:30.918190",
      "details": {
        "success": true,
        "commit_message": "chore: production update from main - 2025-11-22"
      }
    },
    {
      "number": 11,
      "name": "start_server",
      "success": true,
      "duration_seconds": 0.05303502082824707,
      "timestamp": "2025-11-22T13:56:30.971954",
      "details": {
        "success": true,
        "pid": 13539,
        "background": true
      }
    }
  ],
  "files_updated": [
    {
      "path": "production/Backend/*",
      "timestamp": "2025-11-22T13:56:28.683538",
      "details": {
        "action": "sync",
        "details": "  ✅ Copied: connectors/user_data_import/test_files/demo_sample.csv"
      }
    },
    {
      "path": "production/Backend/*",
      "timestamp": "2025-11-22T13:56:28.683543",
      "details": {
        "action": "sync",
        "details": "  ✅ Copied: connectors/user_data_import/test_files/ibkr_sample.csv"
      }
    },
    {
      "path": "production/Backend/*",
      "timestamp": "2025-11-22T13:56:28.683549",
      "details": {
        "action": "sync",
        "details": "  ✅ Copied: scripts/map_active_files.py"
      }
    },
    {
      "path": "production/Backend/*",
      "timestamp": "2025-11-22T13:56:28.683559",
      "details": {
        "action": "sync",
        "details": "✅ Copied: 178 files"
      }
    },
    {
      "path": "production/trading-ui/*",
      "timestamp": "2025-11-22T13:56:28.834339",
      "details": {
        "action": "sync",
        "details": "✅ Successfully copied 570 files"
      }
    },
    {
      "path": "documentation/version-manifest.json",
      "timestamp": "2025-11-22T13:56:29.055495",
      "details": {
        "new_version": "1.2.4.0"
      }
    }
  ],
  "files_new": [
    {
      "path": "/Users/nimrod/Documents/TikTrack/TikTrackApp-Production/production/Backend/db/backups/tiktrack_pre-update_20251122_115628.db",
      "timestamp": "2025-11-22T13:56:28.317989",
      "details": {
        "type": "database_backup",
        "label": "pre-update"
      }
    }
  ],
  "files_deleted": [
    {
      "path": "documentation/*",
      "timestamp": "2025-11-22T13:56:28.288997",
      "reason": "Cleanup removed 0 items"
    }
  ],
  "warnings": [
    {
      "message": "Production settings may need verification",
      "step": "fix_config",
      "timestamp": "2025-11-22T13:56:28.840109"
    },
    {
      "message": "Isolation verification had issues",
      "step": "validate",
      "timestamp": "2025-11-22T13:56:28.950517"
    },
    {
      "message": "Structure verification had issues",
      "step": "validate",
      "timestamp": "2025-11-22T13:56:28.955322"
    },
    {
      "message": "Post-update validation had issues",
      "step": "validate",
      "timestamp": "2025-11-22T13:56:29.017999"
    }
  ],
  "errors": [],
  "summary": {
    "total_duration_seconds": 2.713983,
    "steps_completed": 9,
    "steps_failed": 0,
    "files_updated_count": 6,
    "files_new_count": 1,
    "files_deleted_count": 1,
    "warnings_count": 4,
    "errors_count": 0
  },
  "end_time": "2025-11-22T13:56:30.972211",
  "success": true
}