{
  "production": {
    "version": "1.3.15.0",
    "major": 1,
    "minor": 3,
    "patch": 15,
    "build": 0,
    "commit": "e681f2eca2e2c21aa652e78746375808974f5931",
    "updated_at": "2025-12-06T23:58:04+00:00",
    "notes": "יצירת בסיס נתונים פרודקשן עם מפתחות מסודרים ונתוני דוגמה מלאים"
  },
  "development": {
    "version": "1.3.95.0",
    "major": 1,
    "minor": 3,
    "patch": 95,
    "build": 0,
    "commit": "5a67c6e1adeb18ea15065551c3737d77275fd7b9",
    "updated_at": "2025-12-07T20:12:12+00:00",
    "notes": "Replace old AI analysis modal interface with 3-step wizard and improve error messages"
  }
}
