{
  "production": {
    "version": "1.3.14.5",
    "major": 1,
    "minor": 3,
    "patch": 14,
    "build": 5,
    "commit": "f7825f199ba48d4215a9ed4235d38ea11a13dc08",
    "updated_at": "2025-11-30T11:42:07+00:00",
    "notes": "Final sm-section-server fix"
  },
  "development": {
    "version": "1.3.53.0",
    "major": 1,
    "minor": 3,
    "patch": 53,
    "build": 0,
    "commit": "7e0e3ae1838c32c23599663c245120de024d32f0",
    "updated_at": "2025-12-02T00:19:29+00:00",
    "notes": "Enhance conditions display with plan details and link"
  }
}
