{
  "production": {
    "version": "1.3.17.0",
    "major": 1,
    "minor": 3,
    "patch": 17,
    "build": 0,
    "commit": "c3cea3465bb8d039a6b8f097a952ce5ddf9314b1",
    "updated_at": "2025-12-07T17:20:22+00:00",
    "notes": "Add new API files from main merge"
  },
  "development": {
    "version": "1.3.94.0",
    "major": 1,
    "minor": 3,
    "patch": 94,
    "build": 0,
    "commit": "6ce1411ca4c4e975da85211d5bf7a5efa282ab42",
    "updated_at": "2025-12-07T01:37:09+00:00",
    "notes": "תיקון: סגירת מודול הוספת טיקר לרשימה אחרי שמירה - תיקון CRUDResponseHandler.handleResponse"
  }
}
